{
  "trend": "#櫻井翔のワンナイトスタディ",
  "scraped_at": "2025-12-13T12:39:40.279436",
  "tweet_count": 29,
  "total_replies": 130,
  "image_count": 142,
  "tweets": [
    {
      "author": "フジテレビ",
      "handle": "",
      "text": "Tonight's the night!! For those of you looking forward to it...\nPlease react with \"\"! \n\n◥◣#Sakurai Sho, Tackling It with an All-Night \"All-Nighter\"!◢◤\n　  　   Tonight at 9 PM <Saturday Premium>\n 『#Sakurai Sho's One Night Study』",
      "replies": "88",
      "retweets": "2.4K",
      "likes": "8.3K",
      "timestamp": "2025-12-12T22:50:00.000Z",
      "image_urls": [],
      "thread_replies": [
        {
          "author": "TVガイドWeb【公式】",
          "handle": "",
          "text": "\"#Sho Sakurai's One Night Study\"\nBroadcast tonight\n\nSho Sakurai heads to the Japan Coast Guard with Seiya Sueyoshi\nAlso conducts an all-night interview with Daisuke Miyagawa at USJ\n\nAfter finishing the location shoot, Sakurai says...\n\"At USJ, I related to the common",
          "replies": "13",
          "retweets": "2.1K",
          "likes": "7.9K",
          "timestamp": "2025-12-12T21:01:00.000Z",
          "image_urls": [
            "https://pbs.twimg.com/media/G7-y0ciagAArZwV?format=jpg&name=large",
            "https://pbs.twimg.com/media/G7-y0cvaMAAM24N?format=jpg&name=360x360",
            "https://pbs.twimg.com/media/G7-y0caagAADNnq?format=jpg&name=360x360"
          ],
          "downloaded_images": [
            "_櫻井翔のワンナイトスタディ/tweet_1_reply_1_img_1.jpg",
            "_櫻井翔のワンナイトスタディ/tweet_1_reply_1_img_2.jpg",
            "_櫻井翔のワンナイトスタディ/tweet_1_reply_1_img_3.jpg"
          ]
        },
        {
          "author": "Fannie Mae",
          "handle": "",
          "text": "Quickly and easily evaluate borrowers' income with our award-winning Income Calculator. Let our technology work harder for you, so you can do great work for your borrowers. Learn more.",
          "replies": "2",
          "retweets": "13",
          "likes": "122",
          "timestamp": "",
          "image_urls": [],
          "downloaded_images": []
        },
        {
          "author": "マイナビニュース・エンタメ【公式】",
          "handle": "",
          "text": "Sho Sakurai, Two Reports Received During All-Night Location Shoot with Japan Coast Guard: \"An Incident or Accident Could Happen at Any Moment\"\n\n#櫻井翔 #櫻井翔のワンナイトスタディ #海上保安庁 #USJ http://news.mynavi.jp/article/20251213-3803283…",
          "replies": "1",
          "retweets": "645",
          "likes": "2.5K",
          "timestamp": "2025-12-12T21:00:17.000Z",
          "image_urls": [
            "https://pbs.twimg.com/media/G7_0EGpbIAA0WZD?format=jpg&name=large",
            "https://pbs.twimg.com/media/G7_0ESbboAAln6q?format=jpg&name=360x360",
            "https://pbs.twimg.com/media/G7_0EgrbQAAyq1G?format=jpg&name=360x360"
          ],
          "downloaded_images": [
            "_櫻井翔のワンナイトスタディ/tweet_1_reply_3_img_1.jpg",
            "_櫻井翔のワンナイトスタディ/tweet_1_reply_3_img_2.jpg",
            "_櫻井翔のワンナイトスタディ/tweet_1_reply_3_img_3.jpg"
          ]
        }
      ],
      "reply_count": 3,
      "downloaded_images": []
    },
    {
      "author": "TVガイドWeb【公式】",
      "handle": "",
      "text": "\"#Sho Sakurai's One Night Study\"\nBroadcast tonight\n\nSho Sakurai heads to the Japan Coast Guard with Seiya Sueyoshi\nAlso conducts an all-night interview with Daisuke Miyagawa at USJ\n\nAfter finishing the location shoot, Sakurai says...\n\"At USJ, I related to the common",
      "replies": "13",
      "retweets": "2.1K",
      "likes": "7.9K",
      "timestamp": "2025-12-12T21:01:00.000Z",
      "image_urls": [
        "https://pbs.twimg.com/media/G7-y0ciagAArZwV?format=jpg&name=large",
        "https://pbs.twimg.com/media/G7-y0cvaMAAM24N?format=jpg&name=360x360",
        "https://pbs.twimg.com/media/G7-y0caagAADNnq?format=jpg&name=360x360"
      ],
      "thread_replies": [
        {
          "author": "はる推し活用アカウント",
          "handle": "",
          "text": "リアタイしてます！\n誠也くんの制服姿…ありがとうございます\n\n#櫻井翔のワンナイトスタディ\n#末澤誠也",
          "replies": "",
          "retweets": "",
          "likes": "1",
          "timestamp": "2025-12-13T12:10:30.000Z",
          "image_urls": [],
          "downloaded_images": []
        },
        {
          "author": "GTFO | 10 Chambers",
          "handle": "",
          "text": "Brace yourself for GTFO - a savage, co-op horror shooter where unnatural enemies never stop hunting, and teamwork is your only lifeline. Now 65% off on Steam!",
          "replies": "",
          "retweets": "",
          "likes": "4",
          "timestamp": "",
          "image_urls": [],
          "downloaded_images": []
        },
        {
          "author": "とら",
          "handle": "",
          "text": "I'm so thrilled by Sueyoshi in his uniform!!!! I'll watch it live!!! Please do your best, Sakurai-kun! \n#末澤誠也",
          "replies": "",
          "retweets": "",
          "likes": "5",
          "timestamp": "2025-12-12T22:13:00.000Z",
          "image_urls": [],
          "downloaded_images": []
        },
        {
          "author": "ろびん",
          "handle": "",
          "text": "末…制服姿カッコイイ",
          "replies": "",
          "retweets": "",
          "likes": "",
          "timestamp": "2025-12-12T22:42:37.000Z",
          "image_urls": [],
          "downloaded_images": []
        },
        {
          "author": "ちょこ",
          "handle": "",
          "text": "Sho-kun and Suesama look so cool in their uniforms too~  \nLooking forward to it",
          "replies": "",
          "retweets": "",
          "likes": "1",
          "timestamp": "2025-12-12T22:14:22.000Z",
          "image_urls": [],
          "downloaded_images": []
        },
        {
          "author": "konana",
          "handle": "",
          "text": "誠也くん制服ありがとうございます\nめちゃくちゃかっこいいです\n楽しみにしています",
          "replies": "",
          "retweets": "",
          "likes": "3",
          "timestamp": "2025-12-13T00:34:59.000Z",
          "image_urls": [],
          "downloaded_images": []
        },
        {
          "author": "さくらもち",
          "handle": "",
          "text": "すえの制服姿かっこいい",
          "replies": "",
          "retweets": "",
          "likes": "",
          "timestamp": "2025-12-13T01:28:17.000Z",
          "image_urls": [],
          "downloaded_images": []
        },
        {
          "author": "くまち",
          "handle": "",
          "text": "そちゃしの楽しみです\n櫻井くんのバーバリーのジャケット？可愛いなぁ",
          "replies": "",
          "retweets": "",
          "likes": "1",
          "timestamp": "2025-12-13T08:00:04.000Z",
          "image_urls": [],
          "downloaded_images": []
        },
        {
          "author": "m",
          "handle": "",
          "text": "誠也君が大好き",
          "replies": "",
          "retweets": "",
          "likes": "",
          "timestamp": "2025-12-13T09:33:09.000Z",
          "image_urls": [],
          "downloaded_images": []
        },
        {
          "author": "あおちゃん",
          "handle": "",
          "text": "せーちゃんを見守るそうしの",
          "replies": "",
          "retweets": "",
          "likes": "",
          "timestamp": "2025-12-13T05:11:58.000Z",
          "image_urls": [],
          "downloaded_images": []
        }
      ],
      "reply_count": 10,
      "downloaded_images": [
        "_櫻井翔のワンナイトスタディ/tweet_2_img_1.jpg",
        "_櫻井翔のワンナイトスタディ/tweet_2_img_2.jpg",
        "_櫻井翔のワンナイトスタディ/tweet_2_img_3.jpg"
      ]
    },
    {
      "author": "Fannie Mae",
      "handle": "",
      "text": "Quickly and easily evaluate borrowers' income with our award-winning Income Calculator. Let our technology work harder for you, so you can do great work for your borrowers. Learn more.",
      "replies": "2",
      "retweets": "13",
      "likes": "122",
      "timestamp": "",
      "image_urls": [],
      "thread_replies": [
        {
          "author": "TVガイドWeb【公式】",
          "handle": "",
          "text": "\"#Sho Sakurai's One Night Study\"\nBroadcast tonight\n\nSho Sakurai heads to the Japan Coast Guard with Seiya Sueyoshi\nAlso conducts an all-night interview with Daisuke Miyagawa at USJ\n\nAfter finishing the location shoot, Sakurai says...\n\"At USJ, I related to the common",
          "replies": "13",
          "retweets": "2.1K",
          "likes": "7.9K",
          "timestamp": "2025-12-12T21:01:00.000Z",
          "image_urls": [
            "https://pbs.twimg.com/media/G7-y0ciagAArZwV?format=jpg&name=large",
            "https://pbs.twimg.com/media/G7-y0cvaMAAM24N?format=jpg&name=360x360",
            "https://pbs.twimg.com/media/G7-y0caagAADNnq?format=jpg&name=360x360"
          ],
          "downloaded_images": [
            "_櫻井翔のワンナイトスタディ/tweet_3_reply_1_img_1.jpg",
            "_櫻井翔のワンナイトスタディ/tweet_3_reply_1_img_2.jpg",
            "_櫻井翔のワンナイトスタディ/tweet_3_reply_1_img_3.jpg"
          ]
        },
        {
          "author": "Fannie Mae",
          "handle": "",
          "text": "Quickly and easily evaluate borrowers' income with our award-winning Income Calculator. Let our technology work harder for you, so you can do great work for your borrowers. Learn more.",
          "replies": "2",
          "retweets": "13",
          "likes": "122",
          "timestamp": "",
          "image_urls": [],
          "downloaded_images": []
        },
        {
          "author": "マイナビニュース・エンタメ【公式】",
          "handle": "",
          "text": "Sho Sakurai, Two Reports Received During All-Night Location Shoot with Japan Coast Guard: \"An Incident or Accident Could Happen at Any Moment\"\n\n#櫻井翔 #櫻井翔のワンナイトスタディ #海上保安庁 #USJ http://news.mynavi.jp/article/20251213-3803283…",
          "replies": "1",
          "retweets": "645",
          "likes": "2.5K",
          "timestamp": "2025-12-12T21:00:17.000Z",
          "image_urls": [
            "https://pbs.twimg.com/media/G7_0EGpbIAA0WZD?format=jpg&name=large",
            "https://pbs.twimg.com/media/G7_0ESbboAAln6q?format=jpg&name=360x360",
            "https://pbs.twimg.com/media/G7_0EgrbQAAyq1G?format=jpg&name=360x360"
          ],
          "downloaded_images": [
            "_櫻井翔のワンナイトスタディ/tweet_3_reply_3_img_1.jpg",
            "_櫻井翔のワンナイトスタディ/tweet_3_reply_3_img_2.jpg",
            "_櫻井翔のワンナイトスタディ/tweet_3_reply_3_img_3.jpg"
          ]
        },
        {
          "author": "HIPO",
          "handle": "",
          "text": "土曜プレミアム\n『櫻井翔のワンナイトスタディ』\nhttps://fujitv.co.jp/fujitv/news/20251510.html…\n\n櫻井翔くん\n「第１回目の放送が終わったあと、深夜の徹底取材が印象深かったと自分の周りでも反響が大きくて。そんなスペシャル番組の第２弾放送が出来るのはすごくうれしかったです」\n\n#櫻井翔のワンナイトスタディ #櫻井翔",
          "replies": "1",
          "retweets": "41",
          "likes": "225",
          "timestamp": "2025-12-13T07:30:46.000Z",
          "image_urls": [
            "https://pbs.twimg.com/media/G8CEXxPaMAAr_fJ?format=jpg&name=large"
          ],
          "downloaded_images": [
            "_櫻井翔のワンナイトスタディ/tweet_3_reply_4_img_1.jpg"
          ]
        },
        {
          "author": "オリコンニュース",
          "handle": "",
          "text": "Broadcasting tonight at 9 PM  \n\"SHO Sakurai's One Night Study\"  \n\nExclusive shots included  \nIn the Japan Coast Guard uniform or  \nTransforming into a staff member at USJ  \n\nWhat did he witness firsthand with his \"all-out\" approach  \nhttps://oricon.co.jp/news/2424272/full/?utm_source=Twitter&utm_medium=social&ref_cd=jstw003…  \n\nJoining the",
          "replies": "17",
          "retweets": "819",
          "likes": "3.7K",
          "timestamp": "2025-12-13T03:05:00.000Z",
          "image_urls": [
            "https://pbs.twimg.com/media/G79q0zsbIAA3F5W?format=jpg&name=large",
            "https://pbs.twimg.com/media/G79q0zsagAEWVth?format=jpg&name=large"
          ],
          "downloaded_images": [
            "_櫻井翔のワンナイトスタディ/tweet_3_reply_5_img_1.jpg",
            "_櫻井翔のワンナイトスタディ/tweet_3_reply_5_img_2.jpg"
          ]
        }
      ],
      "reply_count": 5,
      "downloaded_images": []
    },
    {
      "author": "マイナビニュース・エンタメ【公式】",
      "handle": "",
      "text": "Sho Sakurai, Two Reports Received During All-Night Location Shoot with Japan Coast Guard: \"An Incident or Accident Could Happen at Any Moment\"\n\n#櫻井翔 #櫻井翔のワンナイトスタディ #海上保安庁 #USJ http://news.mynavi.jp/article/20251213-3803283…",
      "replies": "1",
      "retweets": "645",
      "likes": "2.5K",
      "timestamp": "2025-12-12T21:00:17.000Z",
      "image_urls": [
        "https://pbs.twimg.com/media/G7_0EGpbIAA0WZD?format=jpg&name=large",
        "https://pbs.twimg.com/media/G7_0ESbboAAln6q?format=jpg&name=360x360",
        "https://pbs.twimg.com/media/G7_0EgrbQAAyq1G?format=jpg&name=360x360"
      ],
      "thread_replies": [
        {
          "author": "めざましmedia",
          "handle": "",
          "text": "Today at 21:00~ \"Sho Sakurai's One Night Study\"\n\nComment from Sho Sakurai has arrived!\n\n\"It's valuable to be able to interview people who are working while everyone else is asleep at night... I enjoyed the location shoot this time as well\"\n\nhttps://mezamashi.media/articles/-/234595…\n\n#末澤誠也",
          "replies": "10",
          "retweets": "1K",
          "likes": "3.7K",
          "timestamp": "2025-12-12T21:00:01.000Z",
          "image_urls": [
            "https://pbs.twimg.com/media/G79QhteagAAmGpo?format=jpg&name=large",
            "https://pbs.twimg.com/media/G79Qk2LagAMlcVa?format=jpg&name=360x360",
            "https://pbs.twimg.com/media/G79Qmv6aYAA0E-2?format=jpg&name=360x360"
          ],
          "downloaded_images": [
            "_櫻井翔のワンナイトスタディ/tweet_4_reply_1_img_1.jpg",
            "_櫻井翔のワンナイトスタディ/tweet_4_reply_1_img_2.jpg",
            "_櫻井翔のワンナイトスタディ/tweet_4_reply_1_img_3.jpg"
          ]
        },
        {
          "author": "オリコンニュース",
          "handle": "",
          "text": "Broadcasting tonight at 9 PM  \n\"SHO Sakurai's One Night Study\"  \n\nExclusive shots included  \nIn the Japan Coast Guard uniform or  \nTransforming into a staff member at USJ  \n\nWhat did he witness firsthand with his \"all-out\" approach  \nhttps://oricon.co.jp/news/2424272/full/?utm_source=Twitter&utm_medium=social&ref_cd=jstw003…  \n\nJoining the",
          "replies": "17",
          "retweets": "821",
          "likes": "3.7K",
          "timestamp": "2025-12-13T03:05:00.000Z",
          "image_urls": [
            "https://pbs.twimg.com/media/G79q0zsbIAA3F5W?format=jpg&name=large",
            "https://pbs.twimg.com/media/G79q0zsagAEWVth?format=jpg&name=large"
          ],
          "downloaded_images": [
            "_櫻井翔のワンナイトスタディ/tweet_4_reply_2_img_1.jpg",
            "_櫻井翔のワンナイトスタディ/tweet_4_reply_2_img_2.jpg"
          ]
        },
        {
          "author": "フジテレビ",
          "handle": "",
          "text": "＼＼Good morning／／\n＼＼This is Fuji TV／／\n\nToday is \"#ShoSakurai'sOneNightStudy\"!!\n\nSatoshi Matsushima & Daiki Shinotsuka (timelesz),\nSeiwa Suezawa (Aえ! group), etc.\nLuxurious guests will appear one after another\n\nThe broadcast starts at 9 PM tonight\nDetails in",
          "replies": "8",
          "retweets": "989",
          "likes": "3K",
          "timestamp": "2025-12-12T22:00:00.000Z",
          "image_urls": [],
          "downloaded_images": []
        },
        {
          "author": "TVガイドWeb【公式】",
          "handle": "",
          "text": "\"#Sho Sakurai's One Night Study\"\nBroadcast tonight\n\nSho Sakurai heads to the Japan Coast Guard with Seiya Sueyoshi\nAlso conducts an all-night interview with Daisuke Miyagawa at USJ\n\nAfter finishing the location shoot, Sakurai says...\n\"At USJ, I related to the common",
          "replies": "13",
          "retweets": "2.1K",
          "likes": "7.9K",
          "timestamp": "2025-12-12T21:01:00.000Z",
          "image_urls": [
            "https://pbs.twimg.com/media/G7-y0ciagAArZwV?format=jpg&name=large",
            "https://pbs.twimg.com/media/G7-y0cvaMAAM24N?format=jpg&name=360x360",
            "https://pbs.twimg.com/media/G7-y0caagAADNnq?format=jpg&name=360x360"
          ],
          "downloaded_images": [
            "_櫻井翔のワンナイトスタディ/tweet_4_reply_4_img_1.jpg",
            "_櫻井翔のワンナイトスタディ/tweet_4_reply_4_img_2.jpg",
            "_櫻井翔のワンナイトスタディ/tweet_4_reply_4_img_3.jpg"
          ]
        },
        {
          "author": "フジテレビ",
          "handle": "",
          "text": "Tonight's the night!! For those of you looking forward to it...\nPlease react with \"\"! \n\n◥◣#Sakurai Sho, Tackling It with an All-Night \"All-Nighter\"!◢◤\n　  　   Tonight at 9 PM <Saturday Premium>\n 『#Sakurai Sho's One Night Study』",
          "replies": "88",
          "retweets": "2.4K",
          "likes": "8.3K",
          "timestamp": "2025-12-12T22:50:00.000Z",
          "image_urls": [],
          "downloaded_images": []
        },
        {
          "author": "TVガイドWeb【公式】",
          "handle": "",
          "text": "\"#Sho Sakurai's One Night Study\"\nBroadcast tonight\n\nSho Sakurai heads to the Japan Coast Guard with Seiya Sueyoshi\nAlso conducts an all-night interview with Daisuke Miyagawa at USJ\n\nAfter finishing the location shoot, Sakurai says...\n\"At USJ, I related to the common",
          "replies": "13",
          "retweets": "2.1K",
          "likes": "7.9K",
          "timestamp": "2025-12-12T21:01:00.000Z",
          "image_urls": [
            "https://pbs.twimg.com/media/G7-y0ciagAArZwV?format=jpg&name=large",
            "https://pbs.twimg.com/media/G7-y0cvaMAAM24N?format=jpg&name=360x360",
            "https://pbs.twimg.com/media/G7-y0caagAADNnq?format=jpg&name=360x360"
          ],
          "downloaded_images": [
            "_櫻井翔のワンナイトスタディ/tweet_4_reply_6_img_1.jpg",
            "_櫻井翔のワンナイトスタディ/tweet_4_reply_6_img_2.jpg",
            "_櫻井翔のワンナイトスタディ/tweet_4_reply_6_img_3.jpg"
          ]
        },
        {
          "author": "Fannie Mae",
          "handle": "",
          "text": "Quickly and easily evaluate borrowers' income with our award-winning Income Calculator. Let our technology work harder for you, so you can do great work for your borrowers. Learn more.",
          "replies": "2",
          "retweets": "13",
          "likes": "122",
          "timestamp": "",
          "image_urls": [],
          "downloaded_images": []
        },
        {
          "author": "マイナビニュース・エンタメ【公式】",
          "handle": "",
          "text": "Sho Sakurai, Two Reports Received During All-Night Location Shoot with Japan Coast Guard: \"An Incident or Accident Could Happen at Any Moment\"\n\n#櫻井翔 #櫻井翔のワンナイトスタディ #海上保安庁 #USJ http://news.mynavi.jp/article/20251213-3803283…",
          "replies": "1",
          "retweets": "647",
          "likes": "2.5K",
          "timestamp": "2025-12-12T21:00:17.000Z",
          "image_urls": [
            "https://pbs.twimg.com/media/G7_0EGpbIAA0WZD?format=jpg&name=large",
            "https://pbs.twimg.com/media/G7_0ESbboAAln6q?format=jpg&name=360x360",
            "https://pbs.twimg.com/media/G7_0EgrbQAAyq1G?format=jpg&name=360x360"
          ],
          "downloaded_images": [
            "_櫻井翔のワンナイトスタディ/tweet_4_reply_8_img_1.jpg",
            "_櫻井翔のワンナイトスタディ/tweet_4_reply_8_img_2.jpg",
            "_櫻井翔のワンナイトスタディ/tweet_4_reply_8_img_3.jpg"
          ]
        },
        {
          "author": "HIPO",
          "handle": "",
          "text": "土曜プレミアム\n『櫻井翔のワンナイトスタディ』\nhttps://fujitv.co.jp/fujitv/news/20251510.html…\n\n櫻井翔くん\n「第１回目の放送が終わったあと、深夜の徹底取材が印象深かったと自分の周りでも反響が大きくて。そんなスペシャル番組の第２弾放送が出来るのはすごくうれしかったです」\n\n#櫻井翔のワンナイトスタディ #櫻井翔",
          "replies": "1",
          "retweets": "41",
          "likes": "225",
          "timestamp": "2025-12-13T07:30:46.000Z",
          "image_urls": [
            "https://pbs.twimg.com/media/G8CEXxPaMAAr_fJ?format=jpg&name=large"
          ],
          "downloaded_images": [
            "_櫻井翔のワンナイトスタディ/tweet_4_reply_9_img_1.jpg"
          ]
        },
        {
          "author": "オリコンニュース",
          "handle": "",
          "text": "Broadcasting tonight at 9 PM  \n\"SHO Sakurai's One Night Study\"  \n\nExclusive shots included  \nIn the Japan Coast Guard uniform or  \nTransforming into a staff member at USJ  \n\nWhat did he witness firsthand with his \"all-out\" approach  \nhttps://oricon.co.jp/news/2424272/full/?utm_source=Twitter&utm_medium=social&ref_cd=jstw003…  \n\nJoining the",
          "replies": "17",
          "retweets": "821",
          "likes": "3.7K",
          "timestamp": "2025-12-13T03:05:00.000Z",
          "image_urls": [
            "https://pbs.twimg.com/media/G79q0zsbIAA3F5W?format=jpg&name=large",
            "https://pbs.twimg.com/media/G79q0zsagAEWVth?format=jpg&name=large"
          ],
          "downloaded_images": [
            "_櫻井翔のワンナイトスタディ/tweet_4_reply_10_img_1.jpg",
            "_櫻井翔のワンナイトスタディ/tweet_4_reply_10_img_2.jpg"
          ]
        }
      ],
      "reply_count": 10,
      "downloaded_images": [
        "_櫻井翔のワンナイトスタディ/tweet_4_img_1.jpg",
        "_櫻井翔のワンナイトスタディ/tweet_4_img_2.jpg",
        "_櫻井翔のワンナイトスタディ/tweet_4_img_3.jpg"
      ]
    },
    {
      "author": "HIPO",
      "handle": "",
      "text": "土曜プレミアム\n『櫻井翔のワンナイトスタディ』\nhttps://fujitv.co.jp/fujitv/news/20251510.html…\n\n櫻井翔くん\n「第１回目の放送が終わったあと、深夜の徹底取材が印象深かったと自分の周りでも反響が大きくて。そんなスペシャル番組の第２弾放送が出来るのはすごくうれしかったです」\n\n#櫻井翔のワンナイトスタディ #櫻井翔",
      "replies": "1",
      "retweets": "41",
      "likes": "225",
      "timestamp": "2025-12-13T07:30:46.000Z",
      "image_urls": [
        "https://pbs.twimg.com/media/G8CEXxPaMAAr_fJ?format=jpg&name=large"
      ],
      "thread_replies": [
        {
          "author": "HIPO",
          "handle": "",
          "text": "◆ 海上保安庁のロケについて\n\n櫻井翔くん\n「救助する方が、ためらいもなくほんの数秒で、ロープ１本をつたい救助を求めている人のもとに飛び降りていかれたのに驚きました。あれが実際海の中で起きたらと考えると、緊迫感は相当なものでしょうし、命を守る、救う仕事って改めてすごいなと」\n\n#櫻井翔",
          "replies": "1",
          "retweets": "11",
          "likes": "67",
          "timestamp": "2025-12-13T07:32:44.000Z",
          "image_urls": [
            "https://pbs.twimg.com/media/G8CE0fWaYAATREs?format=jpg&name=360x360"
          ],
          "downloaded_images": [
            "_櫻井翔のワンナイトスタディ/tweet_5_reply_1_img_1.jpg"
          ]
        },
        {
          "author": "HIPO",
          "handle": "",
          "text": "◆ USJのロケについて\n\n櫻井翔くん\n「ショーのリハーサルの様子も見させていただきましたが、僕もコンサートのリハーサルなどは初日を迎えるまで夜中に及ぶことも多いんです。たくさんの人を笑顔にする、ステージの裏側あるあるみたいなところも感じられて、共感する部分は大きかったです」\n\n#櫻井翔",
          "replies": "",
          "retweets": "11",
          "likes": "64",
          "timestamp": "2025-12-13T07:34:07.000Z",
          "image_urls": [
            "https://pbs.twimg.com/media/G8CFIsiaQAA4gSR?format=jpg&name=360x360"
          ],
          "downloaded_images": [
            "_櫻井翔のワンナイトスタディ/tweet_5_reply_2_img_1.jpg"
          ]
        },
        {
          "author": "Shape of Dreams",
          "handle": "",
          "text": "It’s here!  The Shape of Dreams FREE Update is now available.\n\nForge new power and master new dangers today!",
          "replies": "",
          "retweets": "",
          "likes": "3",
          "timestamp": "",
          "image_urls": [],
          "downloaded_images": []
        },
        {
          "author": "さくぽの",
          "handle": "",
          "text": "\"Sakurai-san's thighs measure 44cm, surprising those around.\"",
          "replies": "1",
          "retweets": "105",
          "likes": "1.2K",
          "timestamp": "2025-12-12T23:22:33.000Z",
          "image_urls": [
            "https://pbs.twimg.com/media/G8AUoYNagAYRnBH?format=jpg&name=360x360"
          ],
          "downloaded_images": [
            "_櫻井翔のワンナイトスタディ/tweet_5_reply_4_img_1.jpg"
          ]
        },
        {
          "author": "Music Credit - ミュージッククレジット",
          "handle": "",
          "text": "#STARTO Wikipedia Access Rankings (2025-12-11)\n1st Sakurai Sho 11230\n2nd Yokoyama Yū 7188\n3rd Meguro Ren 5785\n4th Ōhashi Kazuya 5036\n5th Shinotsuka Daiki 3668\n6th Kimura Takuya 2758\n7th and below ↓https://music-credit.com/ranking/wikipedia/l4/…\n#STARTO",
          "replies": "1",
          "retweets": "113",
          "likes": "443",
          "timestamp": "2025-12-12T03:01:34.000Z",
          "image_urls": [],
          "downloaded_images": []
        },
        {
          "author": "TVガイドWeb【公式】",
          "handle": "",
          "text": "\"#Sho Sakurai's One Night Study\"\nBroadcast tonight\n\nSho Sakurai heads to the Japan Coast Guard with Seiya Sueyoshi\nAlso conducts an all-night interview with Daisuke Miyagawa at USJ\n\nAfter finishing the location shoot, Sakurai says...\n\"At USJ, I related to the common",
          "replies": "13",
          "retweets": "2.1K",
          "likes": "7.9K",
          "timestamp": "2025-12-12T21:01:00.000Z",
          "image_urls": [
            "https://pbs.twimg.com/media/G7-y0ciagAArZwV?format=jpg&name=large",
            "https://pbs.twimg.com/media/G7-y0cvaMAAM24N?format=jpg&name=360x360",
            "https://pbs.twimg.com/media/G7-y0caagAADNnq?format=jpg&name=360x360"
          ],
          "downloaded_images": [
            "_櫻井翔のワンナイトスタディ/tweet_5_reply_6_img_1.jpg",
            "_櫻井翔のワンナイトスタディ/tweet_5_reply_6_img_2.jpg",
            "_櫻井翔のワンナイトスタディ/tweet_5_reply_6_img_3.jpg"
          ]
        },
        {
          "author": "Fannie Mae",
          "handle": "",
          "text": "Quickly and easily evaluate borrowers' income with our award-winning Income Calculator. Let our technology work harder for you, so you can do great work for your borrowers. Learn more.",
          "replies": "2",
          "retweets": "13",
          "likes": "122",
          "timestamp": "",
          "image_urls": [],
          "downloaded_images": []
        },
        {
          "author": "マイナビニュース・エンタメ【公式】",
          "handle": "",
          "text": "Sho Sakurai, Two Reports Received During All-Night Location Shoot with Japan Coast Guard: \"An Incident or Accident Could Happen at Any Moment\"\n\n#櫻井翔 #櫻井翔のワンナイトスタディ #海上保安庁 #USJ http://news.mynavi.jp/article/20251213-3803283…",
          "replies": "1",
          "retweets": "647",
          "likes": "2.5K",
          "timestamp": "2025-12-12T21:00:17.000Z",
          "image_urls": [
            "https://pbs.twimg.com/media/G7_0EGpbIAA0WZD?format=jpg&name=large",
            "https://pbs.twimg.com/media/G7_0ESbboAAln6q?format=jpg&name=360x360",
            "https://pbs.twimg.com/media/G7_0EgrbQAAyq1G?format=jpg&name=360x360"
          ],
          "downloaded_images": [
            "_櫻井翔のワンナイトスタディ/tweet_5_reply_8_img_1.jpg",
            "_櫻井翔のワンナイトスタディ/tweet_5_reply_8_img_2.jpg",
            "_櫻井翔のワンナイトスタディ/tweet_5_reply_8_img_3.jpg"
          ]
        },
        {
          "author": "HIPO",
          "handle": "",
          "text": "土曜プレミアム\n『櫻井翔のワンナイトスタディ』\nhttps://fujitv.co.jp/fujitv/news/20251510.html…\n\n櫻井翔くん\n「第１回目の放送が終わったあと、深夜の徹底取材が印象深かったと自分の周りでも反響が大きくて。そんなスペシャル番組の第２弾放送が出来るのはすごくうれしかったです」\n\n#櫻井翔のワンナイトスタディ #櫻井翔",
          "replies": "1",
          "retweets": "41",
          "likes": "226",
          "timestamp": "2025-12-13T07:30:46.000Z",
          "image_urls": [
            "https://pbs.twimg.com/media/G8CEXxPaMAAr_fJ?format=jpg&name=large"
          ],
          "downloaded_images": [
            "_櫻井翔のワンナイトスタディ/tweet_5_reply_9_img_1.jpg"
          ]
        },
        {
          "author": "オリコンニュース",
          "handle": "",
          "text": "Broadcasting tonight at 9 PM  \n\"SHO Sakurai's One Night Study\"  \n\nExclusive shots included  \nIn the Japan Coast Guard uniform or  \nTransforming into a staff member at USJ  \n\nWhat did he witness firsthand with his \"all-out\" approach  \nhttps://oricon.co.jp/news/2424272/full/?utm_source=Twitter&utm_medium=social&ref_cd=jstw003…  \n\nJoining the",
          "replies": "17",
          "retweets": "821",
          "likes": "3.7K",
          "timestamp": "2025-12-13T03:05:00.000Z",
          "image_urls": [
            "https://pbs.twimg.com/media/G79q0zsbIAA3F5W?format=jpg&name=large",
            "https://pbs.twimg.com/media/G79q0zsagAEWVth?format=jpg&name=large"
          ],
          "downloaded_images": [
            "_櫻井翔のワンナイトスタディ/tweet_5_reply_10_img_1.jpg",
            "_櫻井翔のワンナイトスタディ/tweet_5_reply_10_img_2.jpg"
          ]
        }
      ],
      "reply_count": 10,
      "downloaded_images": [
        "_櫻井翔のワンナイトスタディ/tweet_5_img_1.jpg"
      ]
    },
    {
      "author": "オリコンニュース",
      "handle": "",
      "text": "Broadcasting tonight at 9 PM  \n\"SHO Sakurai's One Night Study\"  \n\nExclusive shots included  \nIn the Japan Coast Guard uniform or  \nTransforming into a staff member at USJ  \n\nWhat did he witness firsthand with his \"all-out\" approach  \nhttps://oricon.co.jp/news/2424272/full/?utm_source=Twitter&utm_medium=social&ref_cd=jstw003…  \n\nJoining the",
      "replies": "17",
      "retweets": "821",
      "likes": "3.7K",
      "timestamp": "2025-12-13T03:05:00.000Z",
      "image_urls": [
        "https://pbs.twimg.com/media/G79q0zsbIAA3F5W?format=jpg&name=large",
        "https://pbs.twimg.com/media/G79q0zsagAEWVth?format=jpg&name=large"
      ],
      "thread_replies": [
        {
          "author": "たむりん",
          "handle": "",
          "text": "Cute\nSho Sakurai's One Night Study\n#Sho Sakurai",
          "replies": "",
          "retweets": "",
          "likes": "3",
          "timestamp": "2025-12-13T04:48:23.000Z",
          "image_urls": [],
          "downloaded_images": []
        },
        {
          "author": "Bradford Exchange",
          "handle": "",
          "text": "250 years of USMC history and heroism, honored in a stately collection of porcelain steins. Shop Now!",
          "replies": "",
          "retweets": "",
          "likes": "9",
          "timestamp": "",
          "image_urls": [],
          "downloaded_images": []
        },
        {
          "author": "sirokuma supairar",
          "handle": "",
          "text": "始まりました",
          "replies": "",
          "retweets": "",
          "likes": "",
          "timestamp": "2025-12-13T12:00:48.000Z",
          "image_urls": [],
          "downloaded_images": []
        },
        {
          "author": "AB",
          "handle": "",
          "text": "翔くんの体当たり挑戦、見逃せない！",
          "replies": "",
          "retweets": "",
          "likes": "",
          "timestamp": "2025-12-13T04:23:15.000Z",
          "image_urls": [],
          "downloaded_images": []
        },
        {
          "author": "Man_like_Future",
          "handle": "",
          "text": "Overall, it seems like it will be engaging content as an \"experiential variety show\" that fuses learning and entertainment.",
          "replies": "",
          "retweets": "",
          "likes": "1",
          "timestamp": "2025-12-13T04:39:57.000Z",
          "image_urls": [],
          "downloaded_images": []
        },
        {
          "author": "Man_like_Future",
          "handle": "",
          "text": "It seems that Sho Sakurai is taking on a style of experiential learning challenge in a short time under the theme of \"One Night Study.\" The program where he dives headfirst into professions and environments that are rarely seen, such as the Japan Coast Guard uniform or a staff",
          "replies": "",
          "retweets": "",
          "likes": "",
          "timestamp": "2025-12-13T04:39:56.000Z",
          "image_urls": [],
          "downloaded_images": []
        },
        {
          "author": "Football Fan",
          "handle": "",
          "text": "ワンナイトスタディ”の本気度が毎回すごい。",
          "replies": "",
          "retweets": "",
          "likes": "1",
          "timestamp": "2025-12-13T03:20:08.000Z",
          "image_urls": [],
          "downloaded_images": []
        },
        {
          "author": "Renandinho",
          "handle": "",
          "text": "",
          "replies": "",
          "retweets": "",
          "likes": "",
          "timestamp": "2025-12-13T03:05:26.000Z",
          "image_urls": [],
          "downloaded_images": []
        },
        {
          "author": "Renandinho",
          "handle": "",
          "text": "",
          "replies": "",
          "retweets": "",
          "likes": "",
          "timestamp": "2025-12-13T03:05:55.000Z",
          "image_urls": [],
          "downloaded_images": []
        },
        {
          "author": "Man_like_Future",
          "handle": "",
          "text": "Additionally, VTR and studio segments will also feature participation from junior members, including timelesz's Matsushima Sō-san, Shinotsuka Daiki-san, Aぇ! group’s Sueyoshi Seiya-san, and others, so it looks like we can enjoy some fresh faces too. Interactions with the juniors",
          "replies": "",
          "retweets": "",
          "likes": "",
          "timestamp": "2025-12-13T04:39:56.000Z",
          "image_urls": [],
          "downloaded_images": []
        }
      ],
      "reply_count": 10,
      "downloaded_images": [
        "_櫻井翔のワンナイトスタディ/tweet_6_img_1.jpg",
        "_櫻井翔のワンナイトスタディ/tweet_6_img_2.jpg"
      ]
    },
    {
      "author": "みい",
      "handle": "",
      "text": "During the flow of asking about the trigger for becoming a coast guard, Sho-kun also asked about Sueyoshi-kun's reason for joining  The flow was too sudden and I laughed, but I directly told Kimura-kun that the trigger was that my mom was a fan, and he said \"Let's take a photo",
      "replies": "",
      "retweets": "",
      "likes": "9",
      "timestamp": "2025-12-13T12:30:50.000Z",
      "image_urls": [
        "https://pbs.twimg.com/media/G8DJDVXaYAA2AbL?format=jpg&name=360x360",
        "https://pbs.twimg.com/media/G8DJDVYawAA2uSr?format=jpg&name=360x360",
        "https://pbs.twimg.com/media/G8DJDVcaEAA1sta?format=jpg&name=360x360",
        "https://pbs.twimg.com/media/G8DJDVVagAA3wEx?format=jpg&name=360x360"
      ],
      "thread_replies": [
        {
          "author": "マイナビニュース・エンタメ【公式】",
          "handle": "",
          "text": "Sho Sakurai, Two Reports Received During All-Night Location Shoot with Japan Coast Guard: \"An Incident or Accident Could Happen at Any Moment\"\n\n#櫻井翔 #櫻井翔のワンナイトスタディ #海上保安庁 #USJ http://news.mynavi.jp/article/20251213-3803283…",
          "replies": "1",
          "retweets": "647",
          "likes": "2.5K",
          "timestamp": "2025-12-12T21:00:17.000Z",
          "image_urls": [
            "https://pbs.twimg.com/media/G7_0EGpbIAA0WZD?format=jpg&name=large",
            "https://pbs.twimg.com/media/G7_0ESbboAAln6q?format=jpg&name=360x360",
            "https://pbs.twimg.com/media/G7_0EgrbQAAyq1G?format=jpg&name=360x360"
          ],
          "downloaded_images": [
            "_櫻井翔のワンナイトスタディ/tweet_7_reply_1_img_1.jpg",
            "_櫻井翔のワンナイトスタディ/tweet_7_reply_1_img_2.jpg",
            "_櫻井翔のワンナイトスタディ/tweet_7_reply_1_img_3.jpg"
          ]
        },
        {
          "author": "HIPO",
          "handle": "",
          "text": "土曜プレミアム\n『櫻井翔のワンナイトスタディ』\nhttps://fujitv.co.jp/fujitv/news/20251510.html…\n\n櫻井翔くん\n「第１回目の放送が終わったあと、深夜の徹底取材が印象深かったと自分の周りでも反響が大きくて。そんなスペシャル番組の第２弾放送が出来るのはすごくうれしかったです」\n\n#櫻井翔のワンナイトスタディ #櫻井翔",
          "replies": "1",
          "retweets": "41",
          "likes": "226",
          "timestamp": "2025-12-13T07:30:46.000Z",
          "image_urls": [
            "https://pbs.twimg.com/media/G8CEXxPaMAAr_fJ?format=jpg&name=large"
          ],
          "downloaded_images": [
            "_櫻井翔のワンナイトスタディ/tweet_7_reply_2_img_1.jpg"
          ]
        },
        {
          "author": "オリコンニュース",
          "handle": "",
          "text": "Broadcasting tonight at 9 PM  \n\"SHO Sakurai's One Night Study\"  \n\nExclusive shots included  \nIn the Japan Coast Guard uniform or  \nTransforming into a staff member at USJ  \n\nWhat did he witness firsthand with his \"all-out\" approach  \nhttps://oricon.co.jp/news/2424272/full/?utm_source=Twitter&utm_medium=social&ref_cd=jstw003…  \n\nJoining the",
          "replies": "17",
          "retweets": "821",
          "likes": "3.7K",
          "timestamp": "2025-12-13T03:05:00.000Z",
          "image_urls": [
            "https://pbs.twimg.com/media/G79q0zsbIAA3F5W?format=jpg&name=large",
            "https://pbs.twimg.com/media/G79q0zsagAEWVth?format=jpg&name=large"
          ],
          "downloaded_images": [
            "_櫻井翔のワンナイトスタディ/tweet_7_reply_3_img_1.jpg",
            "_櫻井翔のワンナイトスタディ/tweet_7_reply_3_img_2.jpg"
          ]
        },
        {
          "author": "みい",
          "handle": "",
          "text": "During the flow of asking about the trigger for becoming a coast guard, Sho-kun also asked about Sueyoshi-kun's reason for joining  The flow was too sudden and I laughed, but I directly told Kimura-kun that the trigger was that my mom was a fan, and he said \"Let's take a photo",
          "replies": "",
          "retweets": "",
          "likes": "14",
          "timestamp": "2025-12-13T12:30:50.000Z",
          "image_urls": [
            "https://pbs.twimg.com/media/G8DJDVXaYAA2AbL?format=jpg&name=360x360",
            "https://pbs.twimg.com/media/G8DJDVYawAA2uSr?format=jpg&name=360x360",
            "https://pbs.twimg.com/media/G8DJDVcaEAA1sta?format=jpg&name=360x360",
            "https://pbs.twimg.com/media/G8DJDVVagAA3wEx?format=jpg&name=360x360"
          ],
          "downloaded_images": [
            "_櫻井翔のワンナイトスタディ/tweet_7_reply_4_img_1.jpg",
            "_櫻井翔のワンナイトスタディ/tweet_7_reply_4_img_2.jpg",
            "_櫻井翔のワンナイトスタディ/tweet_7_reply_4_img_3.jpg",
            "_櫻井翔のワンナイトスタディ/tweet_7_reply_4_img_4.jpg"
          ]
        },
        {
          "author": "フジテレビ",
          "handle": "",
          "text": "＼＼Good morning／／\n＼＼This is Fuji TV／／\n\nToday is \"#ShoSakurai'sOneNightStudy\"!!\n\nSatoshi Matsushima & Daiki Shinotsuka (timelesz),\nSeiwa Suezawa (Aえ! group), etc.\nLuxurious guests will appear one after another\n\nThe broadcast starts at 9 PM tonight\nDetails in",
          "replies": "8",
          "retweets": "990",
          "likes": "3K",
          "timestamp": "2025-12-12T22:00:00.000Z",
          "image_urls": [],
          "downloaded_images": []
        },
        {
          "author": "RBB TODAY",
          "handle": "",
          "text": "Real Emergency Report During Maritime Safety Agency Filming! Sakurai Sho Surprised by the On-Site Tension: \"An Incident or Accident Could Happen Anytime\"\nhttps://rbbtoday.com/article/2025/12/13/240932.html?utm_source=twitter&utm_medium=social&utm_content=tweet…\n\n#櫻井翔のワンナイトスタディ #櫻井翔 #土曜プレミアム #フジテレビ #海上保安庁",
          "replies": "",
          "retweets": "83",
          "likes": "118",
          "timestamp": "2025-12-13T10:42:10.000Z",
          "image_urls": [
            "https://pbs.twimg.com/media/G8CwKO1aYAABGGg?format=jpg&name=large",
            "https://pbs.twimg.com/media/G8CwKmDaUAANtTr?format=jpg&name=360x360",
            "https://pbs.twimg.com/media/G8CwK7hbYAApPMC?format=jpg&name=360x360"
          ],
          "downloaded_images": [
            "_櫻井翔のワンナイトスタディ/tweet_7_reply_6_img_1.jpg",
            "_櫻井翔のワンナイトスタディ/tweet_7_reply_6_img_2.jpg",
            "_櫻井翔のワンナイトスタディ/tweet_7_reply_6_img_3.jpg"
          ]
        },
        {
          "author": "casabrutus",
          "handle": "",
          "text": "ライフスタイルマガジンとしては異例です！ 『Casa BRUTUS』6月号「万博と建築」の重版が決定しました！\nフジテレビ初の単独冠番組として始まった『 #櫻井翔のワンナイトスタディ 』では夜の #大阪・関西万博 を訪れた嵐の #櫻井翔 さん。昼に訪れた模様は『Casa BRUTUS』でぜひご覧ください。",
          "replies": "1",
          "retweets": "427",
          "likes": "838",
          "timestamp": "2025-05-23T08:42:58.000Z",
          "image_urls": [
            "https://pbs.twimg.com/media/GrnYSe8WgAAVA4B?format=jpg&name=large"
          ],
          "downloaded_images": [
            "_櫻井翔のワンナイトスタディ/tweet_7_reply_7_img_1.jpg"
          ]
        },
        {
          "author": "サイトウさん。#不定期",
          "handle": "",
          "text": "この一瞬で元気になった。\n\n#櫻井翔のワンナイトスタディ 20251213\n#櫻井翔",
          "replies": "",
          "retweets": "4",
          "likes": "16",
          "timestamp": "2025-12-13T12:20:30.000Z",
          "image_urls": [],
          "downloaded_images": []
        }
      ],
      "reply_count": 8,
      "downloaded_images": [
        "_櫻井翔のワンナイトスタディ/tweet_7_img_1.jpg",
        "_櫻井翔のワンナイトスタディ/tweet_7_img_2.jpg",
        "_櫻井翔のワンナイトスタディ/tweet_7_img_3.jpg",
        "_櫻井翔のワンナイトスタディ/tweet_7_img_4.jpg"
      ]
    },
    {
      "author": "フジテレビ",
      "handle": "",
      "text": "＼＼Good morning／／\n＼＼This is Fuji TV／／\n\nToday is \"#ShoSakurai'sOneNightStudy\"!!\n\nSatoshi Matsushima & Daiki Shinotsuka (timelesz),\nSeiwa Suezawa (Aえ! group), etc.\nLuxurious guests will appear one after another\n\nThe broadcast starts at 9 PM tonight\nDetails in",
      "replies": "8",
      "retweets": "990",
      "likes": "3K",
      "timestamp": "2025-12-12T22:00:00.000Z",
      "image_urls": [],
      "thread_replies": [
        {
          "author": "オリコンニュース",
          "handle": "",
          "text": "Broadcasting tonight at 9 PM  \n\"SHO Sakurai's One Night Study\"  \n\nExclusive shots included  \nIn the Japan Coast Guard uniform or  \nTransforming into a staff member at USJ  \n\nWhat did he witness firsthand with his \"all-out\" approach  \nhttps://oricon.co.jp/news/2424272/full/?utm_source=Twitter&utm_medium=social&ref_cd=jstw003…  \n\nJoining the",
          "replies": "17",
          "retweets": "821",
          "likes": "3.7K",
          "timestamp": "2025-12-13T03:05:00.000Z",
          "image_urls": [
            "https://pbs.twimg.com/media/G79q0zsbIAA3F5W?format=jpg&name=large",
            "https://pbs.twimg.com/media/G79q0zsagAEWVth?format=jpg&name=large"
          ],
          "downloaded_images": [
            "_櫻井翔のワンナイトスタディ/tweet_8_reply_1_img_1.jpg",
            "_櫻井翔のワンナイトスタディ/tweet_8_reply_1_img_2.jpg"
          ]
        },
        {
          "author": "みい",
          "handle": "",
          "text": "During the flow of asking about the trigger for becoming a coast guard, Sho-kun also asked about Sueyoshi-kun's reason for joining  The flow was too sudden and I laughed, but I directly told Kimura-kun that the trigger was that my mom was a fan, and he said \"Let's take a photo",
          "replies": "",
          "retweets": "",
          "likes": "14",
          "timestamp": "2025-12-13T12:30:50.000Z",
          "image_urls": [
            "https://pbs.twimg.com/media/G8DJDVXaYAA2AbL?format=jpg&name=360x360",
            "https://pbs.twimg.com/media/G8DJDVYawAA2uSr?format=jpg&name=360x360",
            "https://pbs.twimg.com/media/G8DJDVcaEAA1sta?format=jpg&name=360x360",
            "https://pbs.twimg.com/media/G8DJDVVagAA3wEx?format=jpg&name=360x360"
          ],
          "downloaded_images": [
            "_櫻井翔のワンナイトスタディ/tweet_8_reply_2_img_1.jpg",
            "_櫻井翔のワンナイトスタディ/tweet_8_reply_2_img_2.jpg",
            "_櫻井翔のワンナイトスタディ/tweet_8_reply_2_img_3.jpg",
            "_櫻井翔のワンナイトスタディ/tweet_8_reply_2_img_4.jpg"
          ]
        },
        {
          "author": "フジテレビ",
          "handle": "",
          "text": "＼＼Good morning／／\n＼＼This is Fuji TV／／\n\nToday is \"#ShoSakurai'sOneNightStudy\"!!\n\nSatoshi Matsushima & Daiki Shinotsuka (timelesz),\nSeiwa Suezawa (Aえ! group), etc.\nLuxurious guests will appear one after another\n\nThe broadcast starts at 9 PM tonight\nDetails in",
          "replies": "8",
          "retweets": "990",
          "likes": "3K",
          "timestamp": "2025-12-12T22:00:00.000Z",
          "image_urls": [],
          "downloaded_images": []
        },
        {
          "author": "RBB TODAY",
          "handle": "",
          "text": "Real Emergency Report During Maritime Safety Agency Filming! Sakurai Sho Surprised by the On-Site Tension: \"An Incident or Accident Could Happen Anytime\"\nhttps://rbbtoday.com/article/2025/12/13/240932.html?utm_source=twitter&utm_medium=social&utm_content=tweet…\n\n#櫻井翔のワンナイトスタディ #櫻井翔 #土曜プレミアム #フジテレビ #海上保安庁",
          "replies": "",
          "retweets": "83",
          "likes": "118",
          "timestamp": "2025-12-13T10:42:10.000Z",
          "image_urls": [
            "https://pbs.twimg.com/media/G8CwKO1aYAABGGg?format=jpg&name=large",
            "https://pbs.twimg.com/media/G8CwKmDaUAANtTr?format=jpg&name=360x360",
            "https://pbs.twimg.com/media/G8CwK7hbYAApPMC?format=jpg&name=360x360"
          ],
          "downloaded_images": [
            "_櫻井翔のワンナイトスタディ/tweet_8_reply_4_img_1.jpg",
            "_櫻井翔のワンナイトスタディ/tweet_8_reply_4_img_2.jpg",
            "_櫻井翔のワンナイトスタディ/tweet_8_reply_4_img_3.jpg"
          ]
        },
        {
          "author": "casabrutus",
          "handle": "",
          "text": "ライフスタイルマガジンとしては異例です！ 『Casa BRUTUS』6月号「万博と建築」の重版が決定しました！\nフジテレビ初の単独冠番組として始まった『 #櫻井翔のワンナイトスタディ 』では夜の #大阪・関西万博 を訪れた嵐の #櫻井翔 さん。昼に訪れた模様は『Casa BRUTUS』でぜひご覧ください。",
          "replies": "1",
          "retweets": "427",
          "likes": "838",
          "timestamp": "2025-05-23T08:42:58.000Z",
          "image_urls": [
            "https://pbs.twimg.com/media/GrnYSe8WgAAVA4B?format=jpg&name=large"
          ],
          "downloaded_images": [
            "_櫻井翔のワンナイトスタディ/tweet_8_reply_5_img_1.jpg"
          ]
        },
        {
          "author": "サイトウさん。#不定期",
          "handle": "",
          "text": "この一瞬で元気になった。\n\n#櫻井翔のワンナイトスタディ 20251213\n#櫻井翔",
          "replies": "",
          "retweets": "4",
          "likes": "16",
          "timestamp": "2025-12-13T12:20:30.000Z",
          "image_urls": [],
          "downloaded_images": []
        },
        {
          "author": "CS.MONEY",
          "handle": "",
          "text": "Covert Skins skyrocketed recently. Do you have ones? You know what to do!",
          "replies": "",
          "retweets": "1",
          "likes": "20",
          "timestamp": "",
          "image_urls": [],
          "downloaded_images": []
        }
      ],
      "reply_count": 7,
      "downloaded_images": []
    },
    {
      "author": "RBB TODAY",
      "handle": "",
      "text": "Real Emergency Report During Maritime Safety Agency Filming! Sakurai Sho Surprised by the On-Site Tension: \"An Incident or Accident Could Happen Anytime\"\nhttps://rbbtoday.com/article/2025/12/13/240932.html?utm_source=twitter&utm_medium=social&utm_content=tweet…\n\n#櫻井翔のワンナイトスタディ #櫻井翔 #土曜プレミアム #フジテレビ #海上保安庁",
      "replies": "",
      "retweets": "83",
      "likes": "118",
      "timestamp": "2025-12-13T10:42:10.000Z",
      "image_urls": [
        "https://pbs.twimg.com/media/G8CwKO1aYAABGGg?format=jpg&name=large",
        "https://pbs.twimg.com/media/G8CwKmDaUAANtTr?format=jpg&name=360x360",
        "https://pbs.twimg.com/media/G8CwK7hbYAApPMC?format=jpg&name=360x360"
      ],
      "thread_replies": [
        {
          "author": "TBSおすすめ配信info【公式】",
          "handle": "",
          "text": "Sakurai・Ariyoshi #THE_Yokai \n\n＼Tsumabuki with the Seatbelt／\n\n#櫻井翔 #妻夫木聡 #佐藤隆太 が\n4年ぶりに男3人旅へ\n\n親友3人で久々にはしゃぎまくる\n\n「3人旅の次の日は...」\n配信限定トークもお見逃しなく\n\nTBS FREE https://cu.tbs.co.jp/episode/20888_2104389_1000139193?utm_source=twitter&utm_medium=organic…\nTVer",
          "replies": "1",
          "retweets": "174",
          "likes": "394",
          "timestamp": "2025-12-13T03:00:15.000Z",
          "image_urls": [],
          "downloaded_images": []
        },
        {
          "author": "カンテレ",
          "handle": "",
          "text": "Tonight at 9 PM: \"Sho Sakurai's One Night Study\" \n\nSho Sakurai on an all-night location shoot from evening until the next morning  at a hot topic spot \n\nHelicopter dispatch  A night that's way too busy at the Japan Coast Guard in Kitakyushu\nUSJ  What on earth are",
          "replies": "1",
          "retweets": "160",
          "likes": "491",
          "timestamp": "2025-12-13T08:00:01.000Z",
          "image_urls": [],
          "downloaded_images": []
        },
        {
          "author": "ＮＳＴ 新潟総合テレビ",
          "handle": "",
          "text": "Sho Sakurai's One Night Study\nDecember 13th (Sat) 21:00\n\n#櫻井翔 heads to a hot spot for an all-night location shoot!\nHe'll quiz the studio members on what he learned and what surprised him\n\n▼Helicopter deployment! Kazu Laser is shocked by the overly busy night at the North",
          "replies": "",
          "retweets": "142",
          "likes": "514",
          "timestamp": "2025-12-12T21:08:00.000Z",
          "image_urls": [
            "https://pbs.twimg.com/media/G7sErB3bsAAdMGP?format=jpg&name=360x360"
          ],
          "downloaded_images": [
            "_櫻井翔のワンナイトスタディ/tweet_9_reply_3_img_1.jpg"
          ]
        },
        {
          "author": "日テレラグビー",
          "handle": "",
          "text": "League One Opening Match\n\nAppearing on the live broadcast of Sunday's opening match  \n#櫻井翔 will conduct an exclusive interview with  \nTakeyama player and Yamazawa Kyoto player from the Wild Knights on #newszero  \n\nBroadcast tonight at 23:30\n\nLooking forward to it",
          "replies": "",
          "retweets": "294",
          "likes": "1K",
          "timestamp": "2025-12-12T13:35:20.000Z",
          "image_urls": [
            "https://pbs.twimg.com/media/G797QA9bgAE2qyR?format=jpg&name=240x240",
            "https://pbs.twimg.com/media/G797QBAagAQVZxT?format=jpg&name=240x240"
          ],
          "downloaded_images": [
            "_櫻井翔のワンナイトスタディ/tweet_9_reply_4_img_1.jpg",
            "_櫻井翔のワンナイトスタディ/tweet_9_reply_4_img_2.jpg"
          ]
        },
        {
          "author": "オリコンニュース",
          "handle": "",
          "text": "Broadcasting tonight at 9 PM  \n\"SHO Sakurai's One Night Study\"  \n\nExclusive shots included  \nIn the Japan Coast Guard uniform or  \nTransforming into a staff member at USJ  \n\nWhat did he witness firsthand with his \"all-out\" approach  \nhttps://oricon.co.jp/news/2424272/full/?utm_source=Twitter&utm_medium=social&ref_cd=jstw003…  \n\nJoining the",
          "replies": "17",
          "retweets": "821",
          "likes": "3.7K",
          "timestamp": "2025-12-13T03:05:00.000Z",
          "image_urls": [
            "https://pbs.twimg.com/media/G79q0zsbIAA3F5W?format=jpg&name=large",
            "https://pbs.twimg.com/media/G79q0zsagAEWVth?format=jpg&name=large"
          ],
          "downloaded_images": [
            "_櫻井翔のワンナイトスタディ/tweet_9_reply_5_img_1.jpg",
            "_櫻井翔のワンナイトスタディ/tweet_9_reply_5_img_2.jpg"
          ]
        },
        {
          "author": "みい",
          "handle": "",
          "text": "During the flow of asking about the trigger for becoming a coast guard, Sho-kun also asked about Sueyoshi-kun's reason for joining  The flow was too sudden and I laughed, but I directly told Kimura-kun that the trigger was that my mom was a fan, and he said \"Let's take a photo",
          "replies": "",
          "retweets": "",
          "likes": "14",
          "timestamp": "2025-12-13T12:30:50.000Z",
          "image_urls": [
            "https://pbs.twimg.com/media/G8DJDVXaYAA2AbL?format=jpg&name=360x360",
            "https://pbs.twimg.com/media/G8DJDVYawAA2uSr?format=jpg&name=360x360",
            "https://pbs.twimg.com/media/G8DJDVcaEAA1sta?format=jpg&name=360x360",
            "https://pbs.twimg.com/media/G8DJDVVagAA3wEx?format=jpg&name=360x360"
          ],
          "downloaded_images": [
            "_櫻井翔のワンナイトスタディ/tweet_9_reply_6_img_1.jpg",
            "_櫻井翔のワンナイトスタディ/tweet_9_reply_6_img_2.jpg",
            "_櫻井翔のワンナイトスタディ/tweet_9_reply_6_img_3.jpg",
            "_櫻井翔のワンナイトスタディ/tweet_9_reply_6_img_4.jpg"
          ]
        },
        {
          "author": "フジテレビ",
          "handle": "",
          "text": "＼＼Good morning／／\n＼＼This is Fuji TV／／\n\nToday is \"#ShoSakurai'sOneNightStudy\"!!\n\nSatoshi Matsushima & Daiki Shinotsuka (timelesz),\nSeiwa Suezawa (Aえ! group), etc.\nLuxurious guests will appear one after another\n\nThe broadcast starts at 9 PM tonight\nDetails in",
          "replies": "8",
          "retweets": "990",
          "likes": "3K",
          "timestamp": "2025-12-12T22:00:00.000Z",
          "image_urls": [],
          "downloaded_images": []
        },
        {
          "author": "RBB TODAY",
          "handle": "",
          "text": "Real Emergency Report During Maritime Safety Agency Filming! Sakurai Sho Surprised by the On-Site Tension: \"An Incident or Accident Could Happen Anytime\"\nhttps://rbbtoday.com/article/2025/12/13/240932.html?utm_source=twitter&utm_medium=social&utm_content=tweet…\n\n#櫻井翔のワンナイトスタディ #櫻井翔 #土曜プレミアム #フジテレビ #海上保安庁",
          "replies": "",
          "retweets": "84",
          "likes": "124",
          "timestamp": "2025-12-13T10:42:10.000Z",
          "image_urls": [
            "https://pbs.twimg.com/media/G8CwKO1aYAABGGg?format=jpg&name=large",
            "https://pbs.twimg.com/media/G8CwKmDaUAANtTr?format=jpg&name=360x360",
            "https://pbs.twimg.com/media/G8CwK7hbYAApPMC?format=jpg&name=360x360"
          ],
          "downloaded_images": [
            "_櫻井翔のワンナイトスタディ/tweet_9_reply_8_img_1.jpg",
            "_櫻井翔のワンナイトスタディ/tweet_9_reply_8_img_2.jpg",
            "_櫻井翔のワンナイトスタディ/tweet_9_reply_8_img_3.jpg"
          ]
        },
        {
          "author": "casabrutus",
          "handle": "",
          "text": "ライフスタイルマガジンとしては異例です！ 『Casa BRUTUS』6月号「万博と建築」の重版が決定しました！\nフジテレビ初の単独冠番組として始まった『 #櫻井翔のワンナイトスタディ 』では夜の #大阪・関西万博 を訪れた嵐の #櫻井翔 さん。昼に訪れた模様は『Casa BRUTUS』でぜひご覧ください。",
          "replies": "1",
          "retweets": "427",
          "likes": "838",
          "timestamp": "2025-05-23T08:42:58.000Z",
          "image_urls": [
            "https://pbs.twimg.com/media/GrnYSe8WgAAVA4B?format=jpg&name=large"
          ],
          "downloaded_images": [
            "_櫻井翔のワンナイトスタディ/tweet_9_reply_9_img_1.jpg"
          ]
        },
        {
          "author": "サイトウさん。#不定期",
          "handle": "",
          "text": "この一瞬で元気になった。\n\n#櫻井翔のワンナイトスタディ 20251213\n#櫻井翔",
          "replies": "",
          "retweets": "4",
          "likes": "16",
          "timestamp": "2025-12-13T12:20:30.000Z",
          "image_urls": [],
          "downloaded_images": []
        }
      ],
      "reply_count": 10,
      "downloaded_images": [
        "_櫻井翔のワンナイトスタディ/tweet_9_img_1.jpg",
        "_櫻井翔のワンナイトスタディ/tweet_9_img_2.jpg",
        "_櫻井翔のワンナイトスタディ/tweet_9_img_3.jpg"
      ]
    },
    {
      "author": "casabrutus",
      "handle": "",
      "text": "ライフスタイルマガジンとしては異例です！ 『Casa BRUTUS』6月号「万博と建築」の重版が決定しました！\nフジテレビ初の単独冠番組として始まった『 #櫻井翔のワンナイトスタディ 』では夜の #大阪・関西万博 を訪れた嵐の #櫻井翔 さん。昼に訪れた模様は『Casa BRUTUS』でぜひご覧ください。",
      "replies": "1",
      "retweets": "427",
      "likes": "838",
      "timestamp": "2025-05-23T08:42:58.000Z",
      "image_urls": [
        "https://pbs.twimg.com/media/GrnYSe8WgAAVA4B?format=jpg&name=large"
      ],
      "thread_replies": [],
      "reply_count": 0,
      "downloaded_images": [
        "_櫻井翔のワンナイトスタディ/tweet_10_img_1.jpg"
      ]
    },
    {
      "author": "casabrutus",
      "handle": "",
      "text": "ライフスタイルマガジンとしては異例です！ 『Casa BRUTUS』6月号「万博と建築」の重版が決定しました！\nフジテレビ初の単独冠番組として始まった『 #櫻井翔のワンナイトスタディ 』では夜の #大阪・関西万博 を訪れた嵐の #櫻井翔 さん。昼に訪れた模様は『Casa BRUTUS』でぜひご覧ください。",
      "replies": "1",
      "retweets": "427",
      "likes": "838",
      "timestamp": "2025-05-23T08:42:58.000Z",
      "image_urls": [
        "https://pbs.twimg.com/media/GrnYSe8WgAAVA4B?format=jpg&name=large"
      ],
      "thread_replies": [
        {
          "author": "casabrutus",
          "handle": "",
          "text": "ライフスタイルマガジンとしては異例です！ 『Casa BRUTUS』6月号「万博と建築」の重版が決定しました！\nフジテレビ初の単独冠番組として始まった『 #櫻井翔のワンナイトスタディ 』では夜の #大阪・関西万博 を訪れた嵐の #櫻井翔 さん。昼に訪れた模様は『Casa BRUTUS』でぜひご覧ください。",
          "replies": "1",
          "retweets": "427",
          "likes": "838",
          "timestamp": "2025-05-23T08:42:58.000Z",
          "image_urls": [],
          "downloaded_images": []
        },
        {
          "author": "みい",
          "handle": "",
          "text": "During the flow of asking about the trigger for becoming a coast guard, Sho-kun also asked about Sueyoshi-kun's reason for joining  The flow was too sudden and I laughed, but I directly told Kimura-kun that the trigger was that my mom was a fan, and he said \"Let's take a photo",
          "replies": "",
          "retweets": "",
          "likes": "14",
          "timestamp": "2025-12-13T12:30:50.000Z",
          "image_urls": [
            "https://pbs.twimg.com/media/G8DJDVXaYAA2AbL?format=jpg&name=360x360",
            "https://pbs.twimg.com/media/G8DJDVYawAA2uSr?format=jpg&name=360x360",
            "https://pbs.twimg.com/media/G8DJDVcaEAA1sta?format=jpg&name=360x360",
            "https://pbs.twimg.com/media/G8DJDVVagAA3wEx?format=jpg&name=360x360"
          ],
          "downloaded_images": [
            "_櫻井翔のワンナイトスタディ/tweet_11_reply_2_img_1.jpg",
            "_櫻井翔のワンナイトスタディ/tweet_11_reply_2_img_2.jpg",
            "_櫻井翔のワンナイトスタディ/tweet_11_reply_2_img_3.jpg",
            "_櫻井翔のワンナイトスタディ/tweet_11_reply_2_img_4.jpg"
          ]
        },
        {
          "author": "フジテレビ",
          "handle": "",
          "text": "＼＼Good morning／／\n＼＼This is Fuji TV／／\n\nToday is \"#ShoSakurai'sOneNightStudy\"!!\n\nSatoshi Matsushima & Daiki Shinotsuka (timelesz),\nSeiwa Suezawa (Aえ! group), etc.\nLuxurious guests will appear one after another\n\nThe broadcast starts at 9 PM tonight\nDetails in",
          "replies": "8",
          "retweets": "990",
          "likes": "3K",
          "timestamp": "2025-12-12T22:00:00.000Z",
          "image_urls": [],
          "downloaded_images": []
        },
        {
          "author": "RBB TODAY",
          "handle": "",
          "text": "Real Emergency Report During Maritime Safety Agency Filming! Sakurai Sho Surprised by the On-Site Tension: \"An Incident or Accident Could Happen Anytime\"\nhttps://rbbtoday.com/article/2025/12/13/240932.html?utm_source=twitter&utm_medium=social&utm_content=tweet…\n\n#櫻井翔のワンナイトスタディ #櫻井翔 #土曜プレミアム #フジテレビ #海上保安庁",
          "replies": "",
          "retweets": "84",
          "likes": "124",
          "timestamp": "2025-12-13T10:42:10.000Z",
          "image_urls": [
            "https://pbs.twimg.com/media/G8CwKO1aYAABGGg?format=jpg&name=large",
            "https://pbs.twimg.com/media/G8CwKmDaUAANtTr?format=jpg&name=360x360",
            "https://pbs.twimg.com/media/G8CwK7hbYAApPMC?format=jpg&name=360x360"
          ],
          "downloaded_images": [
            "_櫻井翔のワンナイトスタディ/tweet_11_reply_4_img_1.jpg",
            "_櫻井翔のワンナイトスタディ/tweet_11_reply_4_img_2.jpg",
            "_櫻井翔のワンナイトスタディ/tweet_11_reply_4_img_3.jpg"
          ]
        },
        {
          "author": "casabrutus",
          "handle": "",
          "text": "ライフスタイルマガジンとしては異例です！ 『Casa BRUTUS』6月号「万博と建築」の重版が決定しました！\nフジテレビ初の単独冠番組として始まった『 #櫻井翔のワンナイトスタディ 』では夜の #大阪・関西万博 を訪れた嵐の #櫻井翔 さん。昼に訪れた模様は『Casa BRUTUS』でぜひご覧ください。",
          "replies": "1",
          "retweets": "427",
          "likes": "838",
          "timestamp": "2025-05-23T08:42:58.000Z",
          "image_urls": [
            "https://pbs.twimg.com/media/GrnYSe8WgAAVA4B?format=jpg&name=large"
          ],
          "downloaded_images": [
            "_櫻井翔のワンナイトスタディ/tweet_11_reply_5_img_1.jpg"
          ]
        },
        {
          "author": "サイトウさん。#不定期",
          "handle": "",
          "text": "この一瞬で元気になった。\n\n#櫻井翔のワンナイトスタディ 20251213\n#櫻井翔",
          "replies": "",
          "retweets": "4",
          "likes": "16",
          "timestamp": "2025-12-13T12:20:30.000Z",
          "image_urls": [],
          "downloaded_images": []
        },
        {
          "author": "CS.MONEY",
          "handle": "",
          "text": "Covert Skins skyrocketed recently. Do you have ones? You know what to do!",
          "replies": "",
          "retweets": "1",
          "likes": "20",
          "timestamp": "",
          "image_urls": [],
          "downloaded_images": []
        },
        {
          "author": "フジテレビ",
          "handle": "",
          "text": "お待たせいたしました！\nついに今夜放送でございます！\n\n╭━━━━━━━━━━━━━╮\n　#櫻井翔 が徹夜で体当たり！\n╰━━━━━━ｖ━━━━━━╯\n\n今夜7時『#櫻井翔のワンナイトスタディ』\n\n　　◥◣真・夜・中・の◢◤\n\n【ホテルニューオータニ】＆【大阪・関西万博】",
          "replies": "25",
          "retweets": "1.6K",
          "likes": "5.9K",
          "timestamp": "2025-05-21T22:10:00.000Z",
          "image_urls": [],
          "downloaded_images": []
        },
        {
          "author": "TVer",
          "handle": "",
          "text": "／\n12/13(Sat) 9 PM\nWatch \"#Sho Sakurai's One Night Study\" live \n＼\n\n#Sho Sakurai and\n#Seiya Sueyoshi et al. go on an all-night location shoot \nThorough coverage of the Japan Coast Guard & USJ!\n\nWatch live on #TVer here\nhttps://tver.jp/live/simul/lergrvvkt5?utm_campaign=official_normal&utm_medium=referral&utm_source=t.co…\n\n#Aぇǃgroup\n#Daiki",
          "replies": "1",
          "retweets": "736",
          "likes": "2.8K",
          "timestamp": "2025-12-12T13:32:00.000Z",
          "image_urls": [
            "https://pbs.twimg.com/media/G7UXoiNaQAAH1T8?format=jpg&name=large",
            "https://pbs.twimg.com/media/G7UXtgdbAAA3khF?format=jpg&name=360x360",
            "https://pbs.twimg.com/media/G7UX3NCaEAA9kUX?format=jpg&name=360x360"
          ],
          "downloaded_images": [
            "_櫻井翔のワンナイトスタディ/tweet_11_reply_9_img_1.jpg",
            "_櫻井翔のワンナイトスタディ/tweet_11_reply_9_img_2.jpg",
            "_櫻井翔のワンナイトスタディ/tweet_11_reply_9_img_3.jpg"
          ]
        }
      ],
      "reply_count": 9,
      "downloaded_images": [
        "_櫻井翔のワンナイトスタディ/tweet_11_img_1.jpg"
      ]
    },
    {
      "author": "サイトウさん。#不定期",
      "handle": "",
      "text": "この一瞬で元気になった。\n\n#櫻井翔のワンナイトスタディ 20251213\n#櫻井翔",
      "replies": "",
      "retweets": "4",
      "likes": "16",
      "timestamp": "2025-12-13T12:20:30.000Z",
      "image_urls": [],
      "thread_replies": [
        {
          "author": "フジテレビ",
          "handle": "",
          "text": "＼＼Good morning／／\n＼＼This is Fuji TV／／\n\nToday is \"#ShoSakurai'sOneNightStudy\"!!\n\nSatoshi Matsushima & Daiki Shinotsuka (timelesz),\nSeiwa Suezawa (Aえ! group), etc.\nLuxurious guests will appear one after another\n\nThe broadcast starts at 9 PM tonight\nDetails in",
          "replies": "8",
          "retweets": "990",
          "likes": "3K",
          "timestamp": "2025-12-12T22:00:00.000Z",
          "image_urls": [],
          "downloaded_images": []
        },
        {
          "author": "RBB TODAY",
          "handle": "",
          "text": "Real Emergency Report During Maritime Safety Agency Filming! Sakurai Sho Surprised by the On-Site Tension: \"An Incident or Accident Could Happen Anytime\"\nhttps://rbbtoday.com/article/2025/12/13/240932.html?utm_source=twitter&utm_medium=social&utm_content=tweet…\n\n#櫻井翔のワンナイトスタディ #櫻井翔 #土曜プレミアム #フジテレビ #海上保安庁",
          "replies": "",
          "retweets": "84",
          "likes": "124",
          "timestamp": "2025-12-13T10:42:10.000Z",
          "image_urls": [
            "https://pbs.twimg.com/media/G8CwKO1aYAABGGg?format=jpg&name=large",
            "https://pbs.twimg.com/media/G8CwKmDaUAANtTr?format=jpg&name=360x360",
            "https://pbs.twimg.com/media/G8CwK7hbYAApPMC?format=jpg&name=360x360"
          ],
          "downloaded_images": [
            "_櫻井翔のワンナイトスタディ/tweet_12_reply_2_img_1.jpg",
            "_櫻井翔のワンナイトスタディ/tweet_12_reply_2_img_2.jpg",
            "_櫻井翔のワンナイトスタディ/tweet_12_reply_2_img_3.jpg"
          ]
        },
        {
          "author": "casabrutus",
          "handle": "",
          "text": "ライフスタイルマガジンとしては異例です！ 『Casa BRUTUS』6月号「万博と建築」の重版が決定しました！\nフジテレビ初の単独冠番組として始まった『 #櫻井翔のワンナイトスタディ 』では夜の #大阪・関西万博 を訪れた嵐の #櫻井翔 さん。昼に訪れた模様は『Casa BRUTUS』でぜひご覧ください。",
          "replies": "1",
          "retweets": "427",
          "likes": "838",
          "timestamp": "2025-05-23T08:42:58.000Z",
          "image_urls": [
            "https://pbs.twimg.com/media/GrnYSe8WgAAVA4B?format=jpg&name=large"
          ],
          "downloaded_images": [
            "_櫻井翔のワンナイトスタディ/tweet_12_reply_3_img_1.jpg"
          ]
        },
        {
          "author": "サイトウさん。#不定期",
          "handle": "",
          "text": "この一瞬で元気になった。\n\n#櫻井翔のワンナイトスタディ 20251213\n#櫻井翔",
          "replies": "",
          "retweets": "4",
          "likes": "16",
          "timestamp": "2025-12-13T12:20:30.000Z",
          "image_urls": [],
          "downloaded_images": []
        },
        {
          "author": "CS.MONEY",
          "handle": "",
          "text": "Covert Skins skyrocketed recently. Do you have ones? You know what to do!",
          "replies": "",
          "retweets": "1",
          "likes": "20",
          "timestamp": "",
          "image_urls": [],
          "downloaded_images": []
        },
        {
          "author": "フジテレビ",
          "handle": "",
          "text": "お待たせいたしました！\nついに今夜放送でございます！\n\n╭━━━━━━━━━━━━━╮\n　#櫻井翔 が徹夜で体当たり！\n╰━━━━━━ｖ━━━━━━╯\n\n今夜7時『#櫻井翔のワンナイトスタディ』\n\n　　◥◣真・夜・中・の◢◤\n\n【ホテルニューオータニ】＆【大阪・関西万博】",
          "replies": "25",
          "retweets": "1.6K",
          "likes": "5.9K",
          "timestamp": "2025-05-21T22:10:00.000Z",
          "image_urls": [],
          "downloaded_images": []
        },
        {
          "author": "TVer",
          "handle": "",
          "text": "／\n12/13(Sat) 9 PM\nWatch \"#Sho Sakurai's One Night Study\" live \n＼\n\n#Sho Sakurai and\n#Seiya Sueyoshi et al. go on an all-night location shoot \nThorough coverage of the Japan Coast Guard & USJ!\n\nWatch live on #TVer here\nhttps://tver.jp/live/simul/lergrvvkt5?utm_campaign=official_normal&utm_medium=referral&utm_source=t.co…\n\n#Aぇǃgroup\n#Daiki",
          "replies": "1",
          "retweets": "736",
          "likes": "2.8K",
          "timestamp": "2025-12-12T13:32:00.000Z",
          "image_urls": [
            "https://pbs.twimg.com/media/G7UXoiNaQAAH1T8?format=jpg&name=large",
            "https://pbs.twimg.com/media/G7UXtgdbAAA3khF?format=jpg&name=360x360",
            "https://pbs.twimg.com/media/G7UX3NCaEAA9kUX?format=jpg&name=360x360"
          ],
          "downloaded_images": [
            "_櫻井翔のワンナイトスタディ/tweet_12_reply_7_img_1.jpg",
            "_櫻井翔のワンナイトスタディ/tweet_12_reply_7_img_2.jpg",
            "_櫻井翔のワンナイトスタディ/tweet_12_reply_7_img_3.jpg"
          ]
        }
      ],
      "reply_count": 7,
      "downloaded_images": []
    },
    {
      "author": "CS.MONEY",
      "handle": "",
      "text": "Covert Skins skyrocketed recently. Do you have ones? You know what to do!",
      "replies": "",
      "retweets": "1",
      "likes": "20",
      "timestamp": "",
      "image_urls": [],
      "thread_replies": [
        {
          "author": "RBB TODAY",
          "handle": "",
          "text": "Real Emergency Report During Maritime Safety Agency Filming! Sakurai Sho Surprised by the On-Site Tension: \"An Incident or Accident Could Happen Anytime\"\nhttps://rbbtoday.com/article/2025/12/13/240932.html?utm_source=twitter&utm_medium=social&utm_content=tweet…\n\n#櫻井翔のワンナイトスタディ #櫻井翔 #土曜プレミアム #フジテレビ #海上保安庁",
          "replies": "",
          "retweets": "84",
          "likes": "124",
          "timestamp": "2025-12-13T10:42:10.000Z",
          "image_urls": [
            "https://pbs.twimg.com/media/G8CwKO1aYAABGGg?format=jpg&name=large",
            "https://pbs.twimg.com/media/G8CwKmDaUAANtTr?format=jpg&name=360x360",
            "https://pbs.twimg.com/media/G8CwK7hbYAApPMC?format=jpg&name=360x360"
          ],
          "downloaded_images": [
            "_櫻井翔のワンナイトスタディ/tweet_13_reply_1_img_1.jpg",
            "_櫻井翔のワンナイトスタディ/tweet_13_reply_1_img_2.jpg",
            "_櫻井翔のワンナイトスタディ/tweet_13_reply_1_img_3.jpg"
          ]
        },
        {
          "author": "casabrutus",
          "handle": "",
          "text": "ライフスタイルマガジンとしては異例です！ 『Casa BRUTUS』6月号「万博と建築」の重版が決定しました！\nフジテレビ初の単独冠番組として始まった『 #櫻井翔のワンナイトスタディ 』では夜の #大阪・関西万博 を訪れた嵐の #櫻井翔 さん。昼に訪れた模様は『Casa BRUTUS』でぜひご覧ください。",
          "replies": "1",
          "retweets": "427",
          "likes": "838",
          "timestamp": "2025-05-23T08:42:58.000Z",
          "image_urls": [
            "https://pbs.twimg.com/media/GrnYSe8WgAAVA4B?format=jpg&name=large"
          ],
          "downloaded_images": [
            "_櫻井翔のワンナイトスタディ/tweet_13_reply_2_img_1.jpg"
          ]
        },
        {
          "author": "サイトウさん。#不定期",
          "handle": "",
          "text": "この一瞬で元気になった。\n\n#櫻井翔のワンナイトスタディ 20251213\n#櫻井翔",
          "replies": "",
          "retweets": "4",
          "likes": "16",
          "timestamp": "2025-12-13T12:20:30.000Z",
          "image_urls": [],
          "downloaded_images": []
        },
        {
          "author": "CS.MONEY",
          "handle": "",
          "text": "Covert Skins skyrocketed recently. Do you have ones? You know what to do!",
          "replies": "",
          "retweets": "1",
          "likes": "20",
          "timestamp": "",
          "image_urls": [],
          "downloaded_images": []
        },
        {
          "author": "フジテレビ",
          "handle": "",
          "text": "お待たせいたしました！\nついに今夜放送でございます！\n\n╭━━━━━━━━━━━━━╮\n　#櫻井翔 が徹夜で体当たり！\n╰━━━━━━ｖ━━━━━━╯\n\n今夜7時『#櫻井翔のワンナイトスタディ』\n\n　　◥◣真・夜・中・の◢◤\n\n【ホテルニューオータニ】＆【大阪・関西万博】",
          "replies": "25",
          "retweets": "1.6K",
          "likes": "5.9K",
          "timestamp": "2025-05-21T22:10:00.000Z",
          "image_urls": [],
          "downloaded_images": []
        },
        {
          "author": "TVer",
          "handle": "",
          "text": "／\n12/13(Sat) 9 PM\nWatch \"#Sho Sakurai's One Night Study\" live \n＼\n\n#Sho Sakurai and\n#Seiya Sueyoshi et al. go on an all-night location shoot \nThorough coverage of the Japan Coast Guard & USJ!\n\nWatch live on #TVer here\nhttps://tver.jp/live/simul/lergrvvkt5?utm_campaign=official_normal&utm_medium=referral&utm_source=t.co…\n\n#Aぇǃgroup\n#Daiki",
          "replies": "1",
          "retweets": "736",
          "likes": "2.8K",
          "timestamp": "2025-12-12T13:32:00.000Z",
          "image_urls": [
            "https://pbs.twimg.com/media/G7UXoiNaQAAH1T8?format=jpg&name=large",
            "https://pbs.twimg.com/media/G7UXtgdbAAA3khF?format=jpg&name=360x360",
            "https://pbs.twimg.com/media/G7UX3NCaEAA9kUX?format=jpg&name=360x360"
          ],
          "downloaded_images": [
            "_櫻井翔のワンナイトスタディ/tweet_13_reply_6_img_1.jpg",
            "_櫻井翔のワンナイトスタディ/tweet_13_reply_6_img_2.jpg",
            "_櫻井翔のワンナイトスタディ/tweet_13_reply_6_img_3.jpg"
          ]
        },
        {
          "author": "株式会社Zeta(ゼータ)",
          "handle": "",
          "text": "Tonight at 21:00 on Fuji TV  \n『#ShoSakurai's One Night Study』  \nIt's a 2-hour SP!  \n\nOur company handled the Japan Coast Guard and studio recording.  \nPlease tune in!♪  \n\n#FujiTV #ShoSakurai  \n#Zeta #Zeta",
          "replies": "",
          "retweets": "175",
          "likes": "564",
          "timestamp": "2025-12-13T05:53:18.000Z",
          "image_urls": [],
          "downloaded_images": []
        }
      ],
      "reply_count": 7,
      "downloaded_images": []
    },
    {
      "author": "フジテレビ",
      "handle": "",
      "text": "お待たせいたしました！\nついに今夜放送でございます！\n\n╭━━━━━━━━━━━━━╮\n　#櫻井翔 が徹夜で体当たり！\n╰━━━━━━ｖ━━━━━━╯\n\n今夜7時『#櫻井翔のワンナイトスタディ』\n\n　　◥◣真・夜・中・の◢◤\n\n【ホテルニューオータニ】＆【大阪・関西万博】",
      "replies": "25",
      "retweets": "1.6K",
      "likes": "5.9K",
      "timestamp": "2025-05-21T22:10:00.000Z",
      "image_urls": [],
      "thread_replies": [
        {
          "author": "casabrutus",
          "handle": "",
          "text": "ライフスタイルマガジンとしては異例です！ 『Casa BRUTUS』6月号「万博と建築」の重版が決定しました！\nフジテレビ初の単独冠番組として始まった『 #櫻井翔のワンナイトスタディ 』では夜の #大阪・関西万博 を訪れた嵐の #櫻井翔 さん。昼に訪れた模様は『Casa BRUTUS』でぜひご覧ください。",
          "replies": "1",
          "retweets": "427",
          "likes": "838",
          "timestamp": "2025-05-23T08:42:58.000Z",
          "image_urls": [
            "https://pbs.twimg.com/media/GrnYSe8WgAAVA4B?format=jpg&name=large"
          ],
          "downloaded_images": [
            "_櫻井翔のワンナイトスタディ/tweet_14_reply_1_img_1.jpg"
          ]
        },
        {
          "author": "サイトウさん。#不定期",
          "handle": "",
          "text": "この一瞬で元気になった。\n\n#櫻井翔のワンナイトスタディ 20251213\n#櫻井翔",
          "replies": "",
          "retweets": "4",
          "likes": "16",
          "timestamp": "2025-12-13T12:20:30.000Z",
          "image_urls": [],
          "downloaded_images": []
        },
        {
          "author": "CS.MONEY",
          "handle": "",
          "text": "Covert Skins skyrocketed recently. Do you have ones? You know what to do!",
          "replies": "",
          "retweets": "1",
          "likes": "20",
          "timestamp": "",
          "image_urls": [],
          "downloaded_images": []
        },
        {
          "author": "フジテレビ",
          "handle": "",
          "text": "お待たせいたしました！\nついに今夜放送でございます！\n\n╭━━━━━━━━━━━━━╮\n　#櫻井翔 が徹夜で体当たり！\n╰━━━━━━ｖ━━━━━━╯\n\n今夜7時『#櫻井翔のワンナイトスタディ』\n\n　　◥◣真・夜・中・の◢◤\n\n【ホテルニューオータニ】＆【大阪・関西万博】",
          "replies": "25",
          "retweets": "1.6K",
          "likes": "5.9K",
          "timestamp": "2025-05-21T22:10:00.000Z",
          "image_urls": [],
          "downloaded_images": []
        },
        {
          "author": "TVer",
          "handle": "",
          "text": "／\n12/13(Sat) 9 PM\nWatch \"#Sho Sakurai's One Night Study\" live \n＼\n\n#Sho Sakurai and\n#Seiya Sueyoshi et al. go on an all-night location shoot \nThorough coverage of the Japan Coast Guard & USJ!\n\nWatch live on #TVer here\nhttps://tver.jp/live/simul/lergrvvkt5?utm_campaign=official_normal&utm_medium=referral&utm_source=t.co…\n\n#Aぇǃgroup\n#Daiki",
          "replies": "1",
          "retweets": "736",
          "likes": "2.8K",
          "timestamp": "2025-12-12T13:32:00.000Z",
          "image_urls": [
            "https://pbs.twimg.com/media/G7UXoiNaQAAH1T8?format=jpg&name=large",
            "https://pbs.twimg.com/media/G7UXtgdbAAA3khF?format=jpg&name=360x360",
            "https://pbs.twimg.com/media/G7UX3NCaEAA9kUX?format=jpg&name=360x360"
          ],
          "downloaded_images": [
            "_櫻井翔のワンナイトスタディ/tweet_14_reply_5_img_1.jpg",
            "_櫻井翔のワンナイトスタディ/tweet_14_reply_5_img_2.jpg",
            "_櫻井翔のワンナイトスタディ/tweet_14_reply_5_img_3.jpg"
          ]
        },
        {
          "author": "株式会社Zeta(ゼータ)",
          "handle": "",
          "text": "Tonight at 21:00 on Fuji TV  \n『#ShoSakurai's One Night Study』  \nIt's a 2-hour SP!  \n\nOur company handled the Japan Coast Guard and studio recording.  \nPlease tune in!♪  \n\n#FujiTV #ShoSakurai  \n#Zeta #Zeta",
          "replies": "",
          "retweets": "175",
          "likes": "564",
          "timestamp": "2025-12-13T05:53:18.000Z",
          "image_urls": [],
          "downloaded_images": []
        },
        {
          "author": "ｓｕｍｕｐｉ",
          "handle": "",
          "text": "しの衣装と一緒だ☆もある！将生の！！\nさっきの有吉いいeeeeのTikTok\n#櫻井翔のワンナイトスタディ \n篠塚大輝",
          "replies": "1",
          "retweets": "",
          "likes": "4",
          "timestamp": "2025-12-13T12:11:09.000Z",
          "image_urls": [
            "https://pbs.twimg.com/media/G8DEi9kboAAfvvC?format=jpg&name=large",
            "https://pbs.twimg.com/media/G8DEi9hbEAIKVO0?format=jpg&name=large"
          ],
          "downloaded_images": [
            "_櫻井翔のワンナイトスタディ/tweet_14_reply_7_img_1.jpg",
            "_櫻井翔のワンナイトスタディ/tweet_14_reply_7_img_2.jpg"
          ]
        }
      ],
      "reply_count": 7,
      "downloaded_images": []
    },
    {
      "author": "TVer",
      "handle": "",
      "text": "／\n12/13(Sat) 9 PM\nWatch \"#Sho Sakurai's One Night Study\" live \n＼\n\n#Sho Sakurai and\n#Seiya Sueyoshi et al. go on an all-night location shoot \nThorough coverage of the Japan Coast Guard & USJ!\n\nWatch live on #TVer here\nhttps://tver.jp/live/simul/lergrvvkt5?utm_campaign=official_normal&utm_medium=referral&utm_source=t.co…\n\n#Aぇǃgroup\n#Daiki",
      "replies": "1",
      "retweets": "736",
      "likes": "2.8K",
      "timestamp": "2025-12-12T13:32:00.000Z",
      "image_urls": [
        "https://pbs.twimg.com/media/G7UXoiNaQAAH1T8?format=jpg&name=large",
        "https://pbs.twimg.com/media/G7UXtgdbAAA3khF?format=jpg&name=360x360",
        "https://pbs.twimg.com/media/G7UX3NCaEAA9kUX?format=jpg&name=360x360"
      ],
      "thread_replies": [
        {
          "author": "さくらん2",
          "handle": "",
          "text": "#Sho Sakurai's One Night Study  \nThank you for broadcasting the second installment  \nI've been waiting for it!  \nMr. Sakurai who has a fear of heights  \nI wonder if the helicopter is okay  \n#Sho Sakurai",
          "replies": "",
          "retweets": "3",
          "likes": "14",
          "timestamp": "2025-12-05T02:46:56.000Z",
          "image_urls": [],
          "downloaded_images": []
        },
        {
          "author": "Children Who Dance in the Rain",
          "handle": "",
          "text": "From her comfortable life in America, Sophie plunges into India's colorful slums in 'Children Who Dance in the Rain.' Her transformative journey uncovers magic, gratitude, and empathy. \n\nYour purchase writes new stories -- 25% of proceeds directly aid underprivileged children.",
          "replies": "11",
          "retweets": "21",
          "likes": "339",
          "timestamp": "",
          "image_urls": [],
          "downloaded_images": []
        },
        {
          "author": "さくらんぼ",
          "handle": "",
          "text": "Tearfully happy sobbing \nMy junior too \n#櫻井翔のワンナイトスタディ",
          "replies": "",
          "retweets": "",
          "likes": "13",
          "timestamp": "2025-12-04T23:58:40.000Z",
          "image_urls": [],
          "downloaded_images": []
        },
        {
          "author": "monaka",
          "handle": "",
          "text": "I've been waiting for the second installment!!\nI'm also looking forward to the joint appearance with the junior guy♪\n#櫻井翔のワンナイトスタディ\n#櫻井翔 #末澤誠也",
          "replies": "",
          "retweets": "",
          "likes": "12",
          "timestamp": "2025-12-04T23:03:45.000Z",
          "image_urls": [],
          "downloaded_images": []
        },
        {
          "author": "m!d0.k-s.s",
          "handle": "",
          "text": "ずーっと待ってました♡\n素敵で可愛いオフショ\nありがとうございます\n放送楽しみにしてます｡\n#櫻井翔のワンナイトスタディ \n#櫻井翔 \n#末澤誠也\n#宮川大輔",
          "replies": "",
          "retweets": "",
          "likes": "9",
          "timestamp": "2025-12-05T00:03:46.000Z",
          "image_urls": [],
          "downloaded_images": []
        },
        {
          "author": "赤楓",
          "handle": "",
          "text": "第２弾ありがとうございます！\n嬉しいーーー\n#櫻井翔のワンナイトスタディ \n#櫻井翔",
          "replies": "",
          "retweets": "",
          "likes": "7",
          "timestamp": "2025-12-04T23:34:57.000Z",
          "image_urls": [],
          "downloaded_images": []
        },
        {
          "author": "あか音",
          "handle": "",
          "text": "誠也くんの出演ほんとにほんとにうれしいです\n本当にありがとうございます!!!\n#櫻井翔のワンナイトスタディ \n#末澤誠也",
          "replies": "",
          "retweets": "",
          "likes": "6",
          "timestamp": "2025-12-04T23:44:13.000Z",
          "image_urls": [],
          "downloaded_images": []
        }
      ],
      "reply_count": 7,
      "downloaded_images": [
        "_櫻井翔のワンナイトスタディ/tweet_15_img_1.jpg",
        "_櫻井翔のワンナイトスタディ/tweet_15_img_2.jpg",
        "_櫻井翔のワンナイトスタディ/tweet_15_img_3.jpg"
      ]
    },
    {
      "author": "めざましmedia",
      "handle": "",
      "text": "\"Sho Sakurai's One Night Study\"\nSecond Episode Broadcast!\n\nSho Sakurai\nexperiences the first-ever helicopter training for a celebrity & the grueling training of a diver with the Japan Coast Guard\nalongside Seiya Sueyoshi\n\nWitnesses a \"Magical Night\" at USJ with Daisuke Miyagawa\n\nDecember 13 (Sat) 21:00~\n\nhttps://mezamashi.media/articles/-/231597…\n\n#Aぇǃgroup",
      "replies": "22",
      "retweets": "1.9K",
      "likes": "6.7K",
      "timestamp": "2025-12-04T22:30:00.000Z",
      "image_urls": [
        "https://pbs.twimg.com/media/G7UXoiNaQAAH1T8?format=jpg&name=large",
        "https://pbs.twimg.com/media/G7UXtgdbAAA3khF?format=jpg&name=360x360",
        "https://pbs.twimg.com/media/G7UX3NCaEAA9kUX?format=jpg&name=360x360"
      ],
      "thread_replies": [
        {
          "author": "さくらん2",
          "handle": "",
          "text": "#Sho Sakurai's One Night Study  \nThank you for broadcasting the second installment  \nI've been waiting for it!  \nMr. Sakurai who has a fear of heights  \nI wonder if the helicopter is okay  \n#Sho Sakurai",
          "replies": "",
          "retweets": "3",
          "likes": "14",
          "timestamp": "2025-12-05T02:46:56.000Z",
          "image_urls": [],
          "downloaded_images": []
        },
        {
          "author": "Children Who Dance in the Rain",
          "handle": "",
          "text": "From her comfortable life in America, Sophie plunges into India's colorful slums in 'Children Who Dance in the Rain.' Her transformative journey uncovers magic, gratitude, and empathy. \n\nYour purchase writes new stories -- 25% of proceeds directly aid underprivileged children.",
          "replies": "11",
          "retweets": "21",
          "likes": "339",
          "timestamp": "",
          "image_urls": [],
          "downloaded_images": []
        },
        {
          "author": "さくらんぼ",
          "handle": "",
          "text": "Tearfully happy sobbing \nMy junior too \n#櫻井翔のワンナイトスタディ",
          "replies": "",
          "retweets": "",
          "likes": "13",
          "timestamp": "2025-12-04T23:58:40.000Z",
          "image_urls": [],
          "downloaded_images": []
        },
        {
          "author": "monaka",
          "handle": "",
          "text": "I've been waiting for the second installment!!\nI'm also looking forward to the joint appearance with the junior guy♪\n#櫻井翔のワンナイトスタディ\n#櫻井翔 #末澤誠也",
          "replies": "",
          "retweets": "",
          "likes": "12",
          "timestamp": "2025-12-04T23:03:45.000Z",
          "image_urls": [],
          "downloaded_images": []
        },
        {
          "author": "m!d0.k-s.s",
          "handle": "",
          "text": "ずーっと待ってました♡\n素敵で可愛いオフショ\nありがとうございます\n放送楽しみにしてます｡\n#櫻井翔のワンナイトスタディ \n#櫻井翔 \n#末澤誠也\n#宮川大輔",
          "replies": "",
          "retweets": "",
          "likes": "9",
          "timestamp": "2025-12-05T00:03:46.000Z",
          "image_urls": [],
          "downloaded_images": []
        },
        {
          "author": "赤楓",
          "handle": "",
          "text": "第２弾ありがとうございます！\n嬉しいーーー\n#櫻井翔のワンナイトスタディ \n#櫻井翔",
          "replies": "",
          "retweets": "",
          "likes": "7",
          "timestamp": "2025-12-04T23:34:57.000Z",
          "image_urls": [],
          "downloaded_images": []
        },
        {
          "author": "あか音",
          "handle": "",
          "text": "誠也くんの出演ほんとにほんとにうれしいです\n本当にありがとうございます!!!\n#櫻井翔のワンナイトスタディ \n#末澤誠也",
          "replies": "",
          "retweets": "",
          "likes": "6",
          "timestamp": "2025-12-04T23:44:13.000Z",
          "image_urls": [],
          "downloaded_images": []
        },
        {
          "author": "なんこ",
          "handle": "",
          "text": "櫻井翔のワンナイトスタディ第二弾ですって\nキャ〜！ありがとうございます！待ってたよ！\nめちゃめちゃ楽しみ\n\n#櫻井翔のワンナイトスタディ \n#櫻井翔",
          "replies": "",
          "retweets": "",
          "likes": "4",
          "timestamp": "2025-12-05T05:04:51.000Z",
          "image_urls": [],
          "downloaded_images": []
        }
      ],
      "reply_count": 8,
      "downloaded_images": [
        "_櫻井翔のワンナイトスタディ/tweet_16_img_1.jpg",
        "_櫻井翔のワンナイトスタディ/tweet_16_img_2.jpg",
        "_櫻井翔のワンナイトスタディ/tweet_16_img_3.jpg"
      ]
    },
    {
      "author": "さくらん2",
      "handle": "",
      "text": "#Sho Sakurai's One Night Study  \nThank you for broadcasting the second installment  \nI've been waiting for it!  \nMr. Sakurai who has a fear of heights  \nI wonder if the helicopter is okay  \n#Sho Sakurai",
      "replies": "",
      "retweets": "3",
      "likes": "14",
      "timestamp": "2025-12-05T02:46:56.000Z",
      "image_urls": [],
      "thread_replies": [
        {
          "author": "さくらん2",
          "handle": "",
          "text": "#Sho Sakurai's One Night Study  \nThank you for broadcasting the second installment  \nI've been waiting for it!  \nMr. Sakurai who has a fear of heights  \nI wonder if the helicopter is okay  \n#Sho Sakurai",
          "replies": "",
          "retweets": "3",
          "likes": "14",
          "timestamp": "2025-12-05T02:46:56.000Z",
          "image_urls": [],
          "downloaded_images": []
        }
      ],
      "reply_count": 1,
      "downloaded_images": []
    },
    {
      "author": "Children Who Dance in the Rain",
      "handle": "",
      "text": "From her comfortable life in America, Sophie plunges into India's colorful slums in 'Children Who Dance in the Rain.' Her transformative journey uncovers magic, gratitude, and empathy. \n\nYour purchase writes new stories -- 25% of proceeds directly aid underprivileged children.",
      "replies": "11",
      "retweets": "21",
      "likes": "339",
      "timestamp": "",
      "image_urls": [],
      "thread_replies": [],
      "reply_count": 0,
      "downloaded_images": []
    },
    {
      "author": "さくらんぼ",
      "handle": "",
      "text": "Tearfully happy sobbing \nMy junior too \n#櫻井翔のワンナイトスタディ",
      "replies": "",
      "retweets": "",
      "likes": "13",
      "timestamp": "2025-12-04T23:58:40.000Z",
      "image_urls": [],
      "thread_replies": [],
      "reply_count": 0,
      "downloaded_images": []
    },
    {
      "author": "monaka",
      "handle": "",
      "text": "I've been waiting for the second installment!!\nI'm also looking forward to the joint appearance with the junior guy♪\n#櫻井翔のワンナイトスタディ\n#櫻井翔 #末澤誠也",
      "replies": "",
      "retweets": "",
      "likes": "12",
      "timestamp": "2025-12-04T23:03:45.000Z",
      "image_urls": [],
      "thread_replies": [],
      "reply_count": 0,
      "downloaded_images": []
    },
    {
      "author": "m!d0.k-s.s",
      "handle": "",
      "text": "ずーっと待ってました♡\n素敵で可愛いオフショ\nありがとうございます\n放送楽しみにしてます｡\n#櫻井翔のワンナイトスタディ \n#櫻井翔 \n#末澤誠也\n#宮川大輔",
      "replies": "",
      "retweets": "",
      "likes": "9",
      "timestamp": "2025-12-05T00:03:46.000Z",
      "image_urls": [],
      "thread_replies": [],
      "reply_count": 0,
      "downloaded_images": []
    },
    {
      "author": "赤楓",
      "handle": "",
      "text": "第２弾ありがとうございます！\n嬉しいーーー\n#櫻井翔のワンナイトスタディ \n#櫻井翔",
      "replies": "",
      "retweets": "",
      "likes": "7",
      "timestamp": "2025-12-04T23:34:57.000Z",
      "image_urls": [],
      "thread_replies": [],
      "reply_count": 0,
      "downloaded_images": []
    },
    {
      "author": "あか音",
      "handle": "",
      "text": "誠也くんの出演ほんとにほんとにうれしいです\n本当にありがとうございます!!!\n#櫻井翔のワンナイトスタディ \n#末澤誠也",
      "replies": "",
      "retweets": "",
      "likes": "6",
      "timestamp": "2025-12-04T23:44:13.000Z",
      "image_urls": [],
      "thread_replies": [],
      "reply_count": 0,
      "downloaded_images": []
    },
    {
      "author": "なんこ",
      "handle": "",
      "text": "櫻井翔のワンナイトスタディ第二弾ですって\nキャ〜！ありがとうございます！待ってたよ！\nめちゃめちゃ楽しみ\n\n#櫻井翔のワンナイトスタディ \n#櫻井翔",
      "replies": "",
      "retweets": "",
      "likes": "4",
      "timestamp": "2025-12-05T05:04:51.000Z",
      "image_urls": [],
      "thread_replies": [],
      "reply_count": 0,
      "downloaded_images": []
    },
    {
      "author": "ハチみゅう(=^・^=)と王様",
      "handle": "",
      "text": "I've been eagerly awaiting the second broadcast!\nI'm very interested in both locations\nI'm also looking forward to the collaborations with Sueyoshi-kun and Miyagawa Daisuke-san\n#櫻井翔のワンナイトスタディ",
      "replies": "",
      "retweets": "",
      "likes": "3",
      "timestamp": "2025-12-05T04:58:05.000Z",
      "image_urls": [],
      "thread_replies": [],
      "reply_count": 0,
      "downloaded_images": []
    },
    {
      "author": "mskmag510",
      "handle": "",
      "text": "わー待ってました\n翔くんの体当たり的なこういうバラエティがほんとに嬉しいです",
      "replies": "",
      "retweets": "",
      "likes": "2",
      "timestamp": "2025-12-05T02:20:59.000Z",
      "image_urls": [],
      "thread_replies": [],
      "reply_count": 0,
      "downloaded_images": []
    },
    {
      "author": "PragerU",
      "handle": "",
      "text": "The Great American Revival starts in homes & classrooms. \n\nThis holiday, every gift to PragerU is TRIPLE-MATCHED (up to $2,000,000) to keep videos free and reach more young Americans. Turn $100 into $300!\n\nLet’s make truth go further—together.",
      "replies": "5",
      "retweets": "38",
      "likes": "148",
      "timestamp": "",
      "image_urls": [],
      "thread_replies": [],
      "reply_count": 0,
      "downloaded_images": []
    },
    {
      "author": "めざましmedia",
      "handle": "",
      "text": "\"Sho Sakurai's One Night Study\"\nSecond Episode Broadcast!\n\nSho Sakurai\nexperiences the first-ever helicopter training for a celebrity & the grueling training of a diver with the Japan Coast Guard\nalongside Seiya Sueyoshi\n\nWitnesses a \"Magical Night\" at USJ with Daisuke Miyagawa",
      "replies": "22",
      "retweets": "1.9K",
      "likes": "6.7K",
      "timestamp": "2025-12-04T22:30:00.000Z",
      "image_urls": [
        "https://pbs.twimg.com/media/G7UXoiNaQAAH1T8?format=jpg&name=large",
        "https://pbs.twimg.com/media/G7UXtgdbAAA3khF?format=jpg&name=360x360",
        "https://pbs.twimg.com/media/G7UX3NCaEAA9kUX?format=jpg&name=360x360"
      ],
      "thread_replies": [
        {
          "author": "さくらん2",
          "handle": "",
          "text": "#Sho Sakurai's One Night Study  \nThank you for broadcasting the second installment  \nI've been waiting for it!  \nMr. Sakurai who has a fear of heights  \nI wonder if the helicopter is okay  \n#Sho Sakurai",
          "replies": "",
          "retweets": "3",
          "likes": "14",
          "timestamp": "2025-12-05T02:46:56.000Z",
          "image_urls": [],
          "downloaded_images": []
        },
        {
          "author": "Children Who Dance in the Rain",
          "handle": "",
          "text": "From her comfortable life in America, Sophie plunges into India's colorful slums in 'Children Who Dance in the Rain.' Her transformative journey uncovers magic, gratitude, and empathy. \n\nYour purchase writes new stories -- 25% of proceeds directly aid underprivileged children.",
          "replies": "11",
          "retweets": "21",
          "likes": "339",
          "timestamp": "",
          "image_urls": [],
          "downloaded_images": []
        },
        {
          "author": "さくらんぼ",
          "handle": "",
          "text": "Tearfully happy sobbing \nMy junior too \n#櫻井翔のワンナイトスタディ",
          "replies": "",
          "retweets": "",
          "likes": "13",
          "timestamp": "2025-12-04T23:58:40.000Z",
          "image_urls": [],
          "downloaded_images": []
        },
        {
          "author": "monaka",
          "handle": "",
          "text": "I've been waiting for the second installment!!\nI'm also looking forward to the joint appearance with the junior guy♪\n#櫻井翔のワンナイトスタディ\n#櫻井翔 #末澤誠也",
          "replies": "",
          "retweets": "",
          "likes": "12",
          "timestamp": "2025-12-04T23:03:45.000Z",
          "image_urls": [],
          "downloaded_images": []
        },
        {
          "author": "m!d0.k-s.s",
          "handle": "",
          "text": "ずーっと待ってました♡\n素敵で可愛いオフショ\nありがとうございます\n放送楽しみにしてます｡\n#櫻井翔のワンナイトスタディ \n#櫻井翔 \n#末澤誠也\n#宮川大輔",
          "replies": "",
          "retweets": "",
          "likes": "9",
          "timestamp": "2025-12-05T00:03:46.000Z",
          "image_urls": [],
          "downloaded_images": []
        },
        {
          "author": "赤楓",
          "handle": "",
          "text": "第２弾ありがとうございます！\n嬉しいーーー\n#櫻井翔のワンナイトスタディ \n#櫻井翔",
          "replies": "",
          "retweets": "",
          "likes": "7",
          "timestamp": "2025-12-04T23:34:57.000Z",
          "image_urls": [],
          "downloaded_images": []
        },
        {
          "author": "あか音",
          "handle": "",
          "text": "誠也くんの出演ほんとにほんとにうれしいです\n本当にありがとうございます!!!\n#櫻井翔のワンナイトスタディ \n#末澤誠也",
          "replies": "",
          "retweets": "",
          "likes": "6",
          "timestamp": "2025-12-04T23:44:13.000Z",
          "image_urls": [],
          "downloaded_images": []
        },
        {
          "author": "なんこ",
          "handle": "",
          "text": "櫻井翔のワンナイトスタディ第二弾ですって\nキャ〜！ありがとうございます！待ってたよ！\nめちゃめちゃ楽しみ\n\n#櫻井翔のワンナイトスタディ \n#櫻井翔",
          "replies": "",
          "retweets": "",
          "likes": "4",
          "timestamp": "2025-12-05T05:04:51.000Z",
          "image_urls": [],
          "downloaded_images": []
        },
        {
          "author": "ハチみゅう(=^・^=)と王様",
          "handle": "",
          "text": "I've been eagerly awaiting the second broadcast!\nI'm very interested in both locations\nI'm also looking forward to the collaborations with Sueyoshi-kun and Miyagawa Daisuke-san\n#櫻井翔のワンナイトスタディ",
          "replies": "",
          "retweets": "",
          "likes": "3",
          "timestamp": "2025-12-05T04:58:05.000Z",
          "image_urls": [],
          "downloaded_images": []
        },
        {
          "author": "めざましmedia",
          "handle": "",
          "text": "\"Sho Sakurai's One Night Study\"\nSecond Episode Broadcast!\n\nSho Sakurai\nexperiences the first-ever helicopter training for a celebrity & the grueling training of a diver with the Japan Coast Guard\nalongside Seiya Sueyoshi\n\nWitnesses a \"Magical Night\" at USJ with Daisuke Miyagawa",
          "replies": "22",
          "retweets": "1.9K",
          "likes": "6.7K",
          "timestamp": "2025-12-04T22:30:00.000Z",
          "image_urls": [
            "https://pbs.twimg.com/media/G7UXoiNaQAAH1T8?format=jpg&name=large",
            "https://pbs.twimg.com/media/G7UXtgdbAAA3khF?format=jpg&name=360x360",
            "https://pbs.twimg.com/media/G7UX3NCaEAA9kUX?format=jpg&name=360x360"
          ],
          "downloaded_images": [
            "_櫻井翔のワンナイトスタディ/tweet_28_reply_10_img_1.jpg",
            "_櫻井翔のワンナイトスタディ/tweet_28_reply_10_img_2.jpg",
            "_櫻井翔のワンナイトスタディ/tweet_28_reply_10_img_3.jpg"
          ]
        }
      ],
      "reply_count": 10,
      "downloaded_images": [
        "_櫻井翔のワンナイトスタディ/tweet_28_img_1.jpg",
        "_櫻井翔のワンナイトスタディ/tweet_28_img_2.jpg",
        "_櫻井翔のワンナイトスタディ/tweet_28_img_3.jpg"
      ]
    },
    {
      "author": "さくらん2",
      "handle": "",
      "text": "#Sho Sakurai's One Night Study  \nThank you for broadcasting the second installment  \nI've been waiting for it!  \nMr. Sakurai who has a fear of heights  \nI wonder if the helicopter is okay  \n#Sho Sakurai",
      "replies": "",
      "retweets": "3",
      "likes": "14",
      "timestamp": "2025-12-05T02:46:56.000Z",
      "image_urls": [],
      "thread_replies": [
        {
          "author": "さくらん2",
          "handle": "",
          "text": "#Sho Sakurai's One Night Study  \nThank you for broadcasting the second installment  \nI've been waiting for it!  \nMr. Sakurai who has a fear of heights  \nI wonder if the helicopter is okay  \n#Sho Sakurai",
          "replies": "",
          "retweets": "3",
          "likes": "14",
          "timestamp": "2025-12-05T02:46:56.000Z",
          "image_urls": [],
          "downloaded_images": []
        }
      ],
      "reply_count": 1,
      "downloaded_images": []
    }
  ]
}